Workbook

Sheet Resumen
A2: Fecha | B2: 3 | C2: 2023
A7: VENTAS CON IVA | C7: =SUMIFS(ventasdiarias[Total],ventasdiarias[Fecha],">="&DATE(Resumen!$C$2,Resumen!$B$2,1),ventasdiarias[Fecha],"<="&EOMONTH(DATE(Resumen!$C$2,Resumen!$B$2,1),0)) -> 2185.6883 | E7: DOÑA 20% | F7: =IF(C$7>=6000,(C$19/100)*20,"0")+IF(C$7<6000,(C$18/100)*20,"0") -> 4.9595761 | H7: VENTA | I7: =Foraneos!J3 -> 0 | K7: Decripción | L7: Día | M7: Promedio | P7: Quincena | Q7: Mensual + comision
A8: VENTAS SIN IVA | C8: =C7/1.16 -> 1884.214 | E8: KIKI 20% | F8: =IF(C$7>=6000,(C$19/100)*20,"0")+IF(C$7<6000,(C$18/100)*20,"0") -> 4.9595761 | H8: COSTO | I8: =Foraneos!H3 -> 0 | K8: Ventas | L8: 23 | M8: =C7/L8 -> 95.029924 | O8: RAFAEL | P8: 25 | Q8: =P8*2+F9 -> 52.479788
A9: COSTOS SIN IVA | C9: =SUMIFS(ventasdiarias[Costo $],ventasdiarias[Fecha],">="&DATE(Resumen!C2,Resumen!B2,1),ventasdiarias[Fecha],"<="&EOMONTH(DATE(Resumen!C2,Resumen!B2,1),0)) -> 1057.618 | E9: RAFAEL 10% | F9: =IF(C$7>=6000,(C$19/100)*10,"0")+IF(C$7<6000,(C$18/100)*10,"0") -> 2.479788 | H9: UTILIDAD B | I9: =I7-I8 -> 0 | K9: Eventuales | L9: 15 | M9: =C14/L9 -> 20.142825 | O9: DOÑA | P9: 0 | Q9: =P9*2+F7 -> 4.9595761
A10: IVA | C10: =C7-C8 -> 301.47424 | E10: ADM 12% | F10: =IF(C$7>=6000,(C$19/100)*12,"0")+IF(C$7<6000,(C$18/100)*12,"0") -> 2.9757456 | H10: UTILIDAD N | I10: =I9-I11 -> 0 | K10: Proyección | L10: 31 | M10: =M8*L10 -> 2945.9276 | O10: ADM | P10: 25 | Q10: =P10*2+F10 -> 52.975746
A11: CAPITAL BRUTO | C11: =C9+C10 -> 1359.0922 | H11: COMISION | I11: =(I9/100)*20 -> 0 | O11: KIKI | P11: 25 | Q11: =P11*2+F8 -> 54.959576
A12: CAPITAL NETO | C12: =C11-Pagos!B5 -> -194.90776
A13: GASTOS FIJO | C13: ='Gastos F-E'!A3 -> 631.25
A14: GASTOS EVENTUALES | C14: ='Gastos F-E'!B3 -> 302.14238
A15: RETIRADOS | C15: ='Gastos F-E'!C3 -> 120
A16: UTILIDAD BRUTA | C16: =C8-C9 -> 826.59601 | E16: Enero | F16: =SUMIFS(ventasdiarias[Total],ventasdiarias[Fecha],">=1"&$E16&Resumen!$C$2,ventasdiarias[Fecha],"<="&EOMONTH("1"&$E16&Resumen!$C$2,0)) -> 2689.1656
A17: UTILIDA NETA | C17: =C16-(C13+C14+C15)+I10 -> -226.79637 | E17: Febrero | F17: =SUMIFS(ventasdiarias[Total],ventasdiarias[Fecha],">=1"&$E17&Resumen!$C$2,ventasdiarias[Fecha],"<="&EOMONTH("1"&$E17&Resumen!$C$2,0)) -> 0
A18: COMISION DEL 3% | C18: =(C16/100)*3+I11 -> 24.79788 | E18: Marzo | F18: =SUMIFS(ventasdiarias[Total],ventasdiarias[Fecha],">=1"&$E18&Resumen!$C$2,ventasdiarias[Fecha],"<="&EOMONTH("1"&$E18&Resumen!$C$2,0)) -> 2185.6883 | S18: Bs | T18: Dolares
A19: COMISION DEL 10% | C19: =(C16/100)*10+I11 -> 82.659601 | E19: Abril | F19: =SUMIFS(ventasdiarias[Total],ventasdiarias[Fecha],">=1"&$E19&Resumen!$C$2,ventasdiarias[Fecha],"<="&EOMONTH("1"&$E19&Resumen!$C$2,0)) -> 2852.3157 | S19: =SUMIFS(ventasdiarias[Bs efecitivo],ventasdiarias[Fecha],">="&DATE(Resumen!$C$2,Resumen!$B$2,1),ventasdiarias[Fecha],"<="&EOMONTH(DATE(Resumen!$C$2,Resumen!$B$2,1),0))+SUMIFS(ventasdiarias[Pago Movil],ventasdiarias[Fecha],">="&DATE(Resumen!$C$2,Resumen!$B$2,1),ventasdiarias[Fecha],"<="&EOMONTH(DATE(Resumen!$C$2,Resumen!$B$2,1),0))+SUMIFS(ventasdiarias[punto],ventasdiarias[Fecha],">="&DATE(Resumen!$C$2,Resumen!$B$2,1),ventasdiarias[Fecha],"<="&EOMONTH(DATE(Resumen!$C$2,Resumen!$B$2,1),0))-SUMIFS(gastoseventuales[BS],gastoseventuales[FECHA],">="&DATE(Resumen!$C$2,Resumen!$B$2,1),gastoseventuales[FECHA],"<="&EOMONTH(DATE(Resumen!$C$2,Resumen!$B$2,1),0))-SUMIFS(abonos[Bs],abonos[FECHA],">="&DATE(Resumen!$C$2,Resumen!$B$2,1),abonos[FECHA],"<="&EOMONTH(DATE(Resumen!$C$2,Resumen!$B$2,1),0)) -> 5244.15 | T19: =SUMIFS(ventasdiarias[Venta $],ventasdiarias[Fecha],">="&DATE(Resumen!$C$2,Resumen!$B$2,1),ventasdiarias[Fecha],"<="&EOMONTH(DATE(Resumen!$C$2,Resumen!$B$2,1),0))-SUMIFS(gastoseventuales[DOLARES],gastoseventuales[FECHA],">="&DATE(Resumen!$C$2,Resumen!$B$2,1),gastoseventuales[FECHA],"<="&EOMONTH(DATE(Resumen!$C$2,Resumen!$B$2,1),0))-SUMIFS(abonos[DOLARES],abonos[FECHA],">="&DATE(Resumen!$C$2,Resumen!$B$2,1),abonos[FECHA],"<="&EOMONTH(DATE(Resumen!$C$2,Resumen!$B$2,1),0))+SUMIFS(ventasdiarias[Zelle $],ventasdiarias[Fecha],">="&DATE(Resumen!$C$2,Resumen!$B$2,1),ventasdiarias[Fecha],"<="&EOMONTH(DATE(Resumen!$C$2,Resumen!$B$2,1),0)) -> -637.66
A20: TOTAL COMISIONES | C20: =(IF(C7>=5000,C19,"0")+IF(C7<5000,C18,"0")) -> 24.79788 | E20: Mayo | F20: =SUMIFS(ventasdiarias[Total],ventasdiarias[Fecha],">=1"&$E20&Resumen!$C$2,ventasdiarias[Fecha],"<="&EOMONTH("1"&$E20&Resumen!$C$2,0)) -> 2835.2154
A21: % UTILIDAD | C21: =(C8-C9)*(100/C8) -> 43.86954 | E21: Junio | F21: =SUMIFS(ventasdiarias[Total],ventasdiarias[Fecha],">=1"&$E21&Resumen!$C$2,ventasdiarias[Fecha],"<="&EOMONTH("1"&$E21&Resumen!$C$2,0)) -> 0
A22: SALDO CAPITAL | C22: =Pagos!B4 -> -194.90776 | E22: Julio | F22: =SUMIFS(ventasdiarias[Total],ventasdiarias[Fecha],">=1"&$E22&Resumen!$C$2,ventasdiarias[Fecha],"<="&EOMONTH("1"&$E22&Resumen!$C$2,0)) -> 0
E23: Agosto | F23: =SUMIFS(ventasdiarias[Total],ventasdiarias[Fecha],">=1"&$E23&Resumen!$C$2,ventasdiarias[Fecha],"<="&EOMONTH("1"&$E23&Resumen!$C$2,0)) -> 0
E24: Septiembre | F24: =SUMIFS(ventasdiarias[Total],ventasdiarias[Fecha],">=1"&$E24&Resumen!$C$2,ventasdiarias[Fecha],"<="&EOMONTH("1"&$E24&Resumen!$C$2,0)) -> 0
E25: Octubre | F25: =SUMIFS(ventasdiarias[Total],ventasdiarias[Fecha],">=1"&$E25&Resumen!$C$2,ventasdiarias[Fecha],"<="&EOMONTH("1"&$E25&Resumen!$C$2,0)) -> 0
E26: Noviembre | F26: =SUMIFS(ventasdiarias[Total],ventasdiarias[Fecha],">=1"&$E26&Resumen!$C$2,ventasdiarias[Fecha],"<="&EOMONTH("1"&$E26&Resumen!$C$2,0)) -> 0
E27: Diciembre | F27: =SUMIFS(ventasdiarias[Total],ventasdiarias[Fecha],">=1"&$E27&Resumen!$C$2,ventasdiarias[Fecha],"<="&EOMONTH("1"&$E27&Resumen!$C$2,0)) -> 0
E29: Promedio
E30: 4 | F30: =SUM(F16:F27)/E30 -> 2640.5963

Sheet Ventas diarias
B5: Fecha | C5: Dia | D5: Tasa | E5: Costo $ | F5: Bs efecitivo | G5: Pago Movil | H5: Venta $ | I5: Zelle $ | J5: punto | K5: Total | L5: Graficos
B6: 45077 | C6: =TEXT(ventasdiarias[[#This Row],[Fecha]],"dddd") -> miércoles | D6: 26.16 | K6: =ventasdiarias[[#This Row],[Venta $]]+ventasdiarias[[#This Row],[Zelle $]]+(IF(ventasdiarias[[#This Row],[Tasa]]>0,(ventasdiarias[[#This Row],[punto]]+ventasdiarias[[#This Row],[Pago Movil]]+ventasdiarias[[#This Row],[Bs efecitivo]])/ventasdiarias[[#This Row],[Tasa]],"0")) -> 0
B7: 45076 | C7: =TEXT(ventasdiarias[[#This Row],[Fecha]],"dddd") -> martes | D7: 26.25 | E7: 94.55 | F7: 420 | G7: 1004.3 | H7: 120 | K7: =ventasdiarias[[#This Row],[Venta $]]+ventasdiarias[[#This Row],[Zelle $]]+(IF(ventasdiarias[[#This Row],[Tasa]]>0,(ventasdiarias[[#This Row],[punto]]+ventasdiarias[[#This Row],[Pago Movil]]+ventasdiarias[[#This Row],[Bs efecitivo]])/ventasdiarias[[#This Row],[Tasa]],"0")) -> 174.25905
B8: 45075 | C8: =TEXT(ventasdiarias[[#This Row],[Fecha]],"dddd") -> lunes | D8: 26.27 | E8: 23.65 | F8: 0 | G8: 394.06 | H8: 26 | I8: 0 | J8: 0 | K8: =ventasdiarias[[#This Row],[Venta $]]+ventasdiarias[[#This Row],[Zelle $]]+(IF(ventasdiarias[[#This Row],[Tasa]]>0,(ventasdiarias[[#This Row],[punto]]+ventasdiarias[[#This Row],[Pago Movil]]+ventasdiarias[[#This Row],[Bs efecitivo]])/ventasdiarias[[#This Row],[Tasa]],"0")) -> 41.000381
B9: 45073 | C9: =TEXT(ventasdiarias[[#This Row],[Fecha]],"dddd") -> sábado | D9: 26 | E9: 5.55 | G9: 52.24 | H9: 10 | K9: =ventasdiarias[[#This Row],[Venta $]]+ventasdiarias[[#This Row],[Zelle $]]+(IF(ventasdiarias[[#This Row],[Tasa]]>0,(ventasdiarias[[#This Row],[punto]]+ventasdiarias[[#This Row],[Pago Movil]]+ventasdiarias[[#This Row],[Bs efecitivo]])/ventasdiarias[[#This Row],[Tasa]],"0")) -> 12.009231
B10: 45072 | C10: =TEXT(ventasdiarias[[#This Row],[Fecha]],"dddd") -> viernes | D10: 26 | E10: 47 | H10: 70 | J10: 208.78 | K10: =ventasdiarias[[#This Row],[Venta $]]+ventasdiarias[[#This Row],[Zelle $]]+(IF(ventasdiarias[[#This Row],[Tasa]]>0,(ventasdiarias[[#This Row],[punto]]+ventasdiarias[[#This Row],[Pago Movil]]+ventasdiarias[[#This Row],[Bs efecitivo]])/ventasdiarias[[#This Row],[Tasa]],"0")) -> 78.03
B11: 45071 | C11: =TEXT(ventasdiarias[[#This Row],[Fecha]],"dddd") -> jueves | D11: 26 | E11: 7.56 | F11: 130 | H11: 11 | K11: =ventasdiarias[[#This Row],[Venta $]]+ventasdiarias[[#This Row],[Zelle $]]+(IF(ventasdiarias[[#This Row],[Tasa]]>0,(ventasdiarias[[#This Row],[punto]]+ventasdiarias[[#This Row],[Pago Movil]]+ventasdiarias[[#This Row],[Bs efecitivo]])/ventasdiarias[[#This Row],[Tasa]],"0")) -> 16
B12: 45070 | C12: =TEXT(ventasdiarias[[#This Row],[Fecha]],"dddd") -> miércoles | D12: 26 | E12: 70.91 | F12: 10 | G12: 91 | H12: 55 | I12: 0 | J12: 1924 | K12: =ventasdiarias[[#This Row],[Venta $]]+ventasdiarias[[#This Row],[Zelle $]]+(IF(ventasdiarias[[#This Row],[Tasa]]>0,(ventasdiarias[[#This Row],[punto]]+ventasdiarias[[#This Row],[Pago Movil]]+ventasdiarias[[#This Row],[Bs efecitivo]])/ventasdiarias[[#This Row],[Tasa]],"0")) -> 132.88462
B13: 45069 | C13: =TEXT(ventasdiarias[[#This Row],[Fecha]],"dddd") -> martes | D13: 26 | E13: 42.32 | F13: 130 | G13: 832 | H13: 40 | I13: 0 | J13: 0 | K13: =ventasdiarias[[#This Row],[Venta $]]+ventasdiarias[[#This Row],[Zelle $]]+(IF(ventasdiarias[[#This Row],[Tasa]]>0,(ventasdiarias[[#This Row],[punto]]+ventasdiarias[[#This Row],[Pago Movil]]+ventasdiarias[[#This Row],[Bs efecitivo]])/ventasdiarias[[#This Row],[Tasa]],"0")) -> 77
B14: 45068 | C14: =TEXT(ventasdiarias[[#This Row],[Fecha]],"dddd") -> lunes | D14: 26 | E14: 24.12 | F14: 208 | G14: 0 | H14: 50 | I14: 0 | J14: 0 | K14: =ventasdiarias[[#This Row],[Venta $]]+ventasdiarias[[#This Row],[Zelle $]]+(IF(ventasdiarias[[#This Row],[Tasa]]>0,(ventasdiarias[[#This Row],[punto]]+ventasdiarias[[#This Row],[Pago Movil]]+ventasdiarias[[#This Row],[Bs efecitivo]])/ventasdiarias[[#This Row],[Tasa]],"0")) -> 58
B15: 45066 | C15: =TEXT(ventasdiarias[[#This Row],[Fecha]],"dddd") -> sábado | D15: 25.9 | E15: 54.83 | F15: 0 | G15: 600 | H15: 77 | I15: 0 | J15: 0 | K15: =ventasdiarias[[#This Row],[Venta $]]+ventasdiarias[[#This Row],[Zelle $]]+(IF(ventasdiarias[[#This Row],[Tasa]]>0,(ventasdiarias[[#This Row],[punto]]+ventasdiarias[[#This Row],[Pago Movil]]+ventasdiarias[[#This Row],[Bs efecitivo]])/ventasdiarias[[#This Row],[Tasa]],"0")) -> 100.16602
B16: 45065 | C16: =TEXT(ventasdiarias[[#This Row],[Fecha]],"dddd") -> viernes | D16: 25.9 | E16: 20.63 | F16: 129 | G16: 0 | H16: 45 | I16: 0 | J16: 0 | K16: =ventasdiarias[[#This Row],[Venta $]]+ventasdiarias[[#This Row],[Zelle $]]+(IF(ventasdiarias[[#This Row],[Tasa]]>0,(ventasdiarias[[#This Row],[punto]]+ventasdiarias[[#This Row],[Pago Movil]]+ventasdiarias[[#This Row],[Bs efecitivo]])/ventasdiarias[[#This Row],[Tasa]],"0")) -> 49.980695
B17: 45064 | C17: =TEXT(ventasdiarias[[#This Row],[Fecha]],"dddd") -> jueves | D17: 25.81 | E17: 20.1 | F17: 0 | G17: 0 | H17: 20 | I17: 0 | J17: 412.54 | K17: =ventasdiarias[[#This Row],[Venta $]]+ventasdiarias[[#This Row],[Zelle $]]+(IF(ventasdiarias[[#This Row],[Tasa]]>0,(ventasdiarias[[#This Row],[punto]]+ventasdiarias[[#This Row],[Pago Movil]]+ventasdiarias[[#This Row],[Bs efecitivo]])/ventasdiarias[[#This Row],[Tasa]],"0")) -> 35.983727
B18: 45063 | C18: =TEXT(ventasdiarias[[#This Row],[Fecha]],"dddd") -> miércoles | D18: 25.64 | E18: 57.89 | F18: 0 | G18: 76.92 | H18: 113 | I18: 0 | J18: 411.62 | K18: =ventasdiarias[[#This Row],[Venta $]]+ventasdiarias[[#This Row],[Zelle $]]+(IF(ventasdiarias[[#This Row],[Tasa]]>0,(ventasdiarias[[#This Row],[punto]]+ventasdiarias[[#This Row],[Pago Movil]]+ventasdiarias[[#This Row],[Bs efecitivo]])/ventasdiarias[[#This Row],[Tasa]],"0")) -> 132.05382
B19: 45062 | C19: =TEXT(ventasdiarias[[#This Row],[Fecha]],"dddd") -> martes | D19: 25.48 | E19: 130.49 | F19: 25 | G19: 0 | H19: 216 | I19: 0 | J19: 0 | K19: =ventasdiarias[[#This Row],[Venta $]]+ventasdiarias[[#This Row],[Zelle $]]+(IF(ventasdiarias[[#This Row],[Tasa]]>0,(ventasdiarias[[#This Row],[punto]]+ventasdiarias[[#This Row],[Pago Movil]]+ventasdiarias[[#This Row],[Bs efecitivo]])/ventasdiarias[[#This Row],[Tasa]],"0")) -> 216.98116
B20: 45061 | C20: =TEXT(ventasdiarias[[#This Row],[Fecha]],"dddd") -> lunes | D20: 25.43 | E20: 101.47 | F20: 150 | G20: 0 | H20: 133 | I20: 0 | J20: 1017.25 | K20: =ventasdiarias[[#This Row],[Venta $]]+ventasdiarias[[#This Row],[Zelle $]]+(IF(ventasdiarias[[#This Row],[Tasa]]>0,(ventasdiarias[[#This Row],[punto]]+ventasdiarias[[#This Row],[Pago Movil]]+ventasdiarias[[#This Row],[Bs efecitivo]])/ventasdiarias[[#This Row],[Tasa]],"0")) -> 178.90051
B21: 45059 | C21: =TEXT(ventasdiarias[[#This Row],[Fecha]],"dddd") -> sábado | D21: 25.17 | E21: 75.7 | F21: 0 | G21: 2339.56 | H21: 27 | I21: 0 | J21: 381.45 | K21: =ventasdiarias[[#This Row],[Venta $]]+ventasdiarias[[#This Row],[Zelle $]]+(IF(ventasdiarias[[#This Row],[Tasa]]>0,(ventasdiarias[[#This Row],[punto]]+ventasdiarias[[#This Row],[Pago Movil]]+ventasdiarias[[#This Row],[Bs efecitivo]])/ventasdiarias[[#This Row],[Tasa]],"0")) -> 135.10528
B22: 45058 | C22: =TEXT(ventasdiarias[[#This Row],[Fecha]],"dddd") -> viernes | D22: 25.17 | E22: 22.02 | F22: 50 | G22: 886.9 | H22: 5 | I22: 0 | J22: 73.25 | K22: =ventasdiarias[[#This Row],[Venta $]]+ventasdiarias[[#This Row],[Zelle $]]+(IF(ventasdiarias[[#This Row],[Tasa]]>0,(ventasdiarias[[#This Row],[punto]]+ventasdiarias[[#This Row],[Pago Movil]]+ventasdiarias[[#This Row],[Bs efecitivo]])/ventasdiarias[[#This Row],[Tasa]],"0")) -> 45.133095
B23: 45057 | C23: =TEXT(ventasdiarias[[#This Row],[Fecha]],"dddd") -> jueves | D23: 25.17 | E23: 220.09 | F23: 377 | G23: 0 | H23: 294 | I23: 0 | J23: 501 | K23: =ventasdiarias[[#This Row],[Venta $]]+ventasdiarias[[#This Row],[Zelle $]]+(IF(ventasdiarias[[#This Row],[Tasa]]>0,(ventasdiarias[[#This Row],[punto]]+ventasdiarias[[#This Row],[Pago Movil]]+ventasdiarias[[#This Row],[Bs efecitivo]])/ventasdiarias[[#This Row],[Tasa]],"0")) -> 328.8828
... B32: 45047 | C32: =TEXT(ventasdiarias[[#This Row],[Fecha]],"dddd") -> lunes | D32: 24.73 | E32: 66.1 | F32: 3 | G32: 0 | H32: 108 | I32: 20 | J32: 0 | K32: =ventasdiarias[[#This Row],[Venta $]]+ventasdiarias[[#This Row],[Zelle $]]+(IF(ventasdiarias[[#This Row],[Tasa]]>0,(ventasdiarias[[#This Row],[punto]]+ventasdiarias[[#This Row],[Pago Movil]]+ventasdiarias[[#This Row],[Bs efecitivo]])/ventasdiarias[[#This Row],[Tasa]],"0")) -> 128.12131
B33: 45046 | C33: =TEXT(ventasdiarias[[#This Row],[Fecha]],"dddd") -> domingo | D33: 24.71 | K33: =ventasdiarias[[#This Row],[Venta $]]+ventasdiarias[[#This Row],[Zelle $]]+(IF(ventasdiarias[[#This Row],[Tasa]]>0,(ventasdiarias[[#This Row],[punto]]+ventasdiarias[[#This Row],[Pago Movil]]+ventasdiarias[[#This Row],[Bs efecitivo]])/ventasdiarias[[#This Row],[Tasa]],"0")) -> 0
B34: 45045 | C34: =TEXT(ventasdiarias[[#This Row],[Fecha]],"dddd") -> sábado | D34: 24.71 | E34: 70.78 | G34: 370.95 | H34: 105 | K34: =ventasdiarias[[#This Row],[Venta $]]+ventasdiarias[[#This Row],[Zelle $]]+(IF(ventasdiarias[[#This Row],[Tasa]]>0,(ventasdiarias[[#This Row],[punto]]+ventasdiarias[[#This Row],[Pago Movil]]+ventasdiarias[[#This Row],[Bs efecitivo]])/ventasdiarias[[#This Row],[Tasa]],"0")) -> 120.01214
B35: 45044 | C35: =TEXT(ventasdiarias[[#This Row],[Fecha]],"dddd") -> viernes | D35: 24.65 | E35: 128.94 | F35: 130 | H35: 210 | J35: 247.3 | K35: =ventasdiarias[[#This Row],[Venta $]]+ventasdiarias[[#This Row],[Zelle $]]+(IF(ventasdiarias[[#This Row],[Tasa]]>0,(ventasdiarias[[#This Row],[punto]]+ventasdiarias[[#This Row],[Pago Movil]]+ventasdiarias[[#This Row],[Bs efecitivo]])/ventasdiarias[[#This Row],[Tasa]],"0")) -> 225.30629
B36: 45043 | C36: =TEXT(ventasdiarias[[#This Row],[Fecha]],"dddd") -> jueves | D36: 24.63 | E36: 53.41 | F36: 415.2 | H36: 26 | J36: 492.65 | K36: =ventasdiarias[[#This Row],[Venta $]]+ventasdiarias[[#This Row],[Zelle $]]+(IF(ventasdiarias[[#This Row],[Tasa]]>0,(ventasdiarias[[#This Row],[punto]]+ventasdiarias[[#This Row],[Pago Movil]]+ventasdiarias[[#This Row],[Bs efecitivo]])/ventasdiarias[[#This Row],[Tasa]],"0")) -> 62.859521
B37: 45042 | C37: =TEXT(ventasdiarias[[#This Row],[Fecha]],"dddd") -> miércoles | D37: 24.65 | E37: 17.34 | H37: 31 | K37: =ventasdiarias[[#This Row],[Venta $]]+ventasdiarias[[#This Row],[Zelle $]]+(IF(ventasdiarias[[#This Row],[Tasa]]>0,(ventasdiarias[[#This Row],[punto]]+ventasdiarias[[#This Row],[Pago Movil]]+ventasdiarias[[#This Row],[Bs efecitivo]])/ventasdiarias[[#This Row],[Tasa]],"0")) -> 31
B38: 45041 | C38: =TEXT(ventasdiarias[[#This Row],[Fecha]],"dddd") -> martes | D38: 24.65 | E38: 62.02 | G38: 689.08 | H38: 89 | K38: =ventasdiarias[[#This Row],[Venta $]]+ventasdiarias[[#This Row],[Zelle $]]+(IF(ventasdiarias[[#This Row],[Tasa]]>0,(ventasdiarias[[#This Row],[punto]]+ventasdiarias[[#This Row],[Pago Movil]]+ventasdiarias[[#This Row],[Bs efecitivo]])/ventasdiarias[[#This Row],[Tasa]],"0")) -> 116.95456
B39: 45040 | C39: =TEXT(ventasdiarias[[#This Row],[Fecha]],"dddd") -> lunes | D39: 24.67 | E39: 52.08 | G39: 986 | H39: 47 | K39: =ventasdiarias[[#This Row],[Venta $]]+ventasdiarias[[#This Row],[Zelle $]]+(IF(ventasdiarias[[#This Row],[Tasa]]>0,(ventasdiarias[[#This Row],[punto]]+ventasdiarias[[#This Row],[Pago Movil]]+ventasdiarias[[#This Row],[Bs efecitivo]])/ventasdiarias[[#This Row],[Tasa]],"0")) -> 86.967572
B40: 45038 | C40: =TEXT(ventasdiarias[[#This Row],[Fecha]],"dddd") -> sábado | D40: 24.57 | E40: 38.44 | H40: 85 | K40: =ventasdiarias[[#This Row],[Venta $]]+ventasdiarias[[#This Row],[Zelle $]]+(IF(ventasdiarias[[#This Row],[Tasa]]>0,(ventasdiarias[[#This Row],[punto]]+ventasdiarias[[#This Row],[Pago Movil]]+ventasdiarias[[#This Row],[Bs efecitivo]])/ventasdiarias[[#This Row],[Tasa]],"0")) -> 85
B41: 45037 | C41: =TEXT(ventasdiarias[[#This Row],[Fecha]],"dddd") -> viernes | D41: 24.57 | E41: -56.33 | H41: 103 | K41: =ventasdiarias[[#This Row],[Venta $]]+ventasdiarias[[#This Row],[Zelle $]]+(IF(ventasdiarias[[#This Row],[Tasa]]>0,(ventasdiarias[[#This Row],[punto]]+ventasdiarias[[#This Row],[Pago Movil]]+ventasdiarias[[#This Row],[Bs efecitivo]])/ventasdiarias[[#This Row],[Tasa]],"0")) -> 103
B42: 45036 | C42: =TEXT(ventasdiarias[[#This Row],[Fecha]],"dddd") -> jueves | D42: 24.57 | E42: 28.5 | F42: 122 | H42: 45 | K42: =ventasdiarias[[#This Row],[Venta $]]+ventasdiarias[[#This Row],[Zelle $]]+(IF(ventasdiarias[[#This Row],[Tasa]]>0,(ventasdiarias[[#This Row],[punto]]+ventasdiarias[[#This Row],[Pago Movil]]+ventasdiarias[[#This Row],[Bs efecitivo]])/ventasdiarias[[#This Row],[Tasa]],"0")) -> 49.965405
B43: 45035 | C43: =TEXT(ventasdiarias[[#This Row],[Fecha]],"dddd") -> miércoles | D43: 24.57 | E43: 104.87 | F43: 73 | H43: 138 | J43: 786.24 | K43: =ventasdiarias[[#This Row],[Venta $]]+ventasdiarias[[#This Row],[Zelle $]]+(IF(ventasdiarias[[#This Row],[Tasa]]>0,(ventasdiarias[[#This Row],[punto]]+ventasdiarias[[#This Row],[Pago Movil]]+ventasdiarias[[#This Row],[Bs efecitivo]])/ventasdiarias[[#This Row],[Tasa]],"0")) -> 172.9711
B44: 45034 | C44: =TEXT(ventasdiarias[[#This Row],[Fecha]],"dddd") -> martes | D44: 24.56 | K44: =ventasdiarias[[#This Row],[Venta $]]+ventasdiarias[[#This Row],[Zelle $]]+(IF(ventasdiarias[[#This Row],[Tasa]]>0,(ventasdiarias[[#This Row],[punto]]+ventasdiarias[[#This Row],[Pago Movil]]+ventasdiarias[[#This Row],[Bs efecitivo]])/ventasdiarias[[#This Row],[Tasa]],"0")) -> 0
B45: 45033 | C45: =TEXT(ventasdiarias[[#This Row],[Fecha]],"dddd") -> lunes | D45: 24.57 | E45: 139.82 | F45: 69 | H45: 255 | K45: =ventasdiarias[[#This Row],[Venta $]]+ventasdiarias[[#This Row],[Zelle $]]+(IF(ventasdiarias[[#This Row],[Tasa]]>0,(ventasdiarias[[#This Row],[punto]]+ventasdiarias[[#This Row],[Pago Movil]]+ventasdiarias[[#This Row],[Bs efecitivo]])/ventasdiarias[[#This Row],[Tasa]],"0")) -> 257.8083
B46: 45031 | C46: =TEXT(ventasdiarias[[#This Row],[Fecha]],"dddd") -> sábado | D46: 24.54 | E46: 293 | G46: 1593.05 | H46: 450 | K46: =ventasdiarias[[#This Row],[Venta $]]+ventasdiarias[[#This Row],[Zelle $]]+(IF(ventasdiarias[[#This Row],[Tasa]]>0,(ventasdiarias[[#This Row],[punto]]+ventasdiarias[[#This Row],[Pago Movil]]+ventasdiarias[[#This Row],[Bs efecitivo]])/ventasdiarias[[#This Row],[Tasa]],"0")) -> 514.91646
B47: 45030 | C47: =TEXT(ventasdiarias[[#This Row],[Fecha]],"dddd") -> viernes | D47: 24.54 | E47: 99.59 | G47: 540.4 | H47: 206 | K47: =ventasdiarias[[#This Row],[Venta $]]+ventasdiarias[[#This Row],[Zelle $]]+(IF(ventasdiarias[[#This Row],[Tasa]]>0,(ventasdiarias[[#This Row],[punto]]+ventasdiarias[[#This Row],[Pago Movil]]+ventasdiarias[[#This Row],[Bs efecitivo]])/ventasdiarias[[#This Row],[Tasa]],"0")) -> 228.02119
B48: 45029 | C48: =TEXT(ventasdiarias[[#This Row],[Fecha]],"dddd") -> jueves | D48: 24.48 | E48: 17.53 | H48: 10 | K48: =ventasdiarias[[#This Row],[Venta $]]+ventasdiarias[[#This Row],[Zelle $]]+(IF(ventasdiarias[[#This Row],[Tasa]]>0,(ventasdiarias[[#This Row],[punto]]+ventasdiarias[[#This Row],[Pago Movil]]+ventasdiarias[[#This Row],[Bs efecitivo]])/ventasdiarias[[#This Row],[Tasa]],"0")) -> 10
B49: 45028 | C49: =TEXT(ventasdiarias[[#This Row],[Fecha]],"dddd") -> miércoles | D49: 24.39 | E49: 10.2 | H49: 20 | K49: =ventasdiarias[[#This Row],[Venta $]]+ventasdiarias[[#This Row],[Zelle $]]+(IF(ventasdiarias[[#This Row],[Tasa]]>0,(ventasdiarias[[#This Row],[punto]]+ventasdiarias[[#This Row],[Pago Movil]]+ventasdiarias[[#This Row],[Bs efecitivo]])/ventasdiarias[[#This Row],[Tasa]],"0")) -> 20
B50: 45027 | C50: =TEXT(ventasdiarias[[#This Row],[Fecha]],"dddd") -> martes | D50: 24.39 | E50: 65.69 | F50: 0 | G50: 0 | H50: 120 | I50: 0 | J50: 122.4 | K50: =ventasdiarias[[#This Row],[Venta $]]+ventasdiarias[[#This Row],[Zelle $]]+(IF(ventasdiarias[[#This Row],[Tasa]]>0,(ventasdiarias[[#This Row],[punto]]+ventasdiarias[[#This Row],[Pago Movil]]+ventasdiarias[[#This Row],[Bs efecitivo]])/ventasdiarias[[#This Row],[Tasa]],"0")) -> 125.01845
B51: 45026 | C51: =TEXT(ventasdiarias[[#This Row],[Fecha]],"dddd") -> lunes | D51: 24.44 | E51: 128.74 | F51: 0 | G51: 122 | H51: 243 | I51: 0 | J51: 0 | K51: =ventasdiarias[[#This Row],[Venta $]]+ventasdiarias[[#This Row],[Zelle $]]+(IF(ventasdiarias[[#This Row],[Tasa]]>0,(ventasdiarias[[#This Row],[punto]]+ventasdiarias[[#This Row],[Pago Movil]]+ventasdiarias[[#This Row],[Bs efecitivo]])/ventasdiarias[[#This Row],[Tasa]],"0")) -> 247.99182
B52: 45021 | C52: =TEXT(ventasdiarias[[#This Row],[Fecha]],"dddd") -> miércoles | D52: 24.44 | E52: 69.012 | F52: 0 | G52: 0 | H52: 120 | I52: 0 | J52: 0 | K52: =ventasdiarias[[#This Row],[Venta $]]+ventasdiarias[[#This Row],[Zelle $]]+(IF(ventasdiarias[[#This Row],[Tasa]]>0,(ventasdiarias[[#This Row],[punto]]+ventasdiarias[[#This Row],[Pago Movil]]+ventasdiarias[[#This Row],[Bs efecitivo]])/ventasdiarias[[#This Row],[Tasa]],"0")) -> 120
B53: 45020 | C53: =TEXT(ventasdiarias[[#This Row],[Fecha]],"dddd") -> martes | D53: 24.48 | E53: 59.44 | F53: 0 | G53: 343.2 | H53: 95 | I53: 0 | J53: 0 | K53: =ventasdiarias[[#This Row],[Venta $]]+ventasdiarias[[#This Row],[Zelle $]]+(IF(ventasdiarias[[#This Row],[Tasa]]>0,(ventasdiarias[[#This Row],[punto]]+ventasdiarias[[#This Row],[Pago Movil]]+ventasdiarias[[#This Row],[Bs efecitivo]])/ventasdiarias[[#This Row],[Tasa]],"0")) -> 109.01961
B54: 45019 | C54: =TEXT(ventasdiarias[[#This Row],[Fecha]],"dddd") -> lunes | D54: 24.52 | E54: 105 | F54: 0 | G54: 147.2 | H54: 154 | I54: 0 | J54: 0 | K54: =ventasdiarias[[#This Row],[Venta $]]+ventasdiarias[[#This Row],[Zelle $]]+(IF(ventasdiarias[[#This Row],[Tasa]]>0,(ventasdiarias[[#This Row],[punto]]+ventasdiarias[[#This Row],[Pago Movil]]+ventasdiarias[[#This Row],[Bs efecitivo]])/ventasdiarias[[#This Row],[Tasa]],"0")) -> 160.00326
B55: 45017 | C55: =TEXT(ventasdiarias[[#This Row],[Fecha]],"dddd") -> sábado | D55: 24.5 | E55: 2.3 | H55: 5.5 | K55: =ventasdiarias[[#This Row],[Venta $]]+ventasdiarias[[#This Row],[Zelle $]]+(IF(ventasdiarias[[#This Row],[Tasa]]>0,(ventasdiarias[[#This Row],[punto]]+ventasdiarias[[#This Row],[Pago Movil]]+ventasdiarias[[#This Row],[Bs efecitivo]])/ventasdiarias[[#This Row],[Tasa]],"0")) -> 5.5
B56: 45016 | C56: =TEXT(ventasdiarias[[#This Row],[Fecha]],"dddd") -> viernes | D56: 24.48 | K56: =ventasdiarias[[#This Row],[Venta $]]+ventasdiarias[[#This Row],[Zelle $]]+(IF(ventasdiarias[[#This Row],[Tasa]]>0,(ventasdiarias[[#This Row],[punto]]+ventasdiarias[[#This Row],[Pago Movil]]+ventasdiarias[[#This Row],[Bs efecitivo]])/ventasdiarias[[#This Row],[Tasa]],"0")) -> 0
B57: 45015 | C57: =TEXT(ventasdiarias[[#This Row],[Fecha]],"dddd") -> jueves | D57: 24.48 | E57: 23.9 | F57: 0 | G57: 0 | H57: 48 | I57: 0 | J57: 0 | K57: =ventasdiarias[[#This Row],[Venta $]]+ventasdiarias[[#This Row],[Zelle $]]+(IF(ventasdiarias[[#This Row],[Tasa]]>0,(ventasdiarias[[#This Row],[punto]]+ventasdiarias[[#This Row],[Pago Movil]]+ventasdiarias[[#This Row],[Bs efecitivo]])/ventasdiarias[[#This Row],[Tasa]],"0")) -> 48
B58: 45014 | C58: =TEXT(ventasdiarias[[#This Row],[Fecha]],"dddd") -> miércoles | D58: 24.48 | E58: 12.45 | F58: 0 | G58: 0 | H58: 22.5 | I58: 0 | J58: 0 | K58: =ventasdiarias[[#This Row],[Venta $]]+ventasdiarias[[#This Row],[Zelle $]]+(IF(ventasdiarias[[#This Row],[Tasa]]>0,(ventasdiarias[[#This Row],[punto]]+ventasdiarias[[#This Row],[Pago Movil]]+ventasdiarias[[#This Row],[Bs efecitivo]])/ventasdiarias[[#This Row],[Tasa]],"0")) -> 22.5
B59: 45013 | C59: =TEXT(ventasdiarias[[#This Row],[Fecha]],"dddd") -> martes | D59: 24.4 | E59: 47.07 | F59: 0 | G59: 0 | H59: 55 | I59: 0 | J59: 830 | K59: =ventasdiarias[[#This Row],[Venta $]]+ventasdiarias[[#This Row],[Zelle $]]+(IF(ventasdiarias[[#This Row],[Tasa]]>0,(ventasdiarias[[#This Row],[punto]]+ventasdiarias[[#This Row],[Pago Movil]]+ventasdiarias[[#This Row],[Bs efecitivo]])/ventasdiarias[[#This Row],[Tasa]],"0")) -> 89.016393
B60: 45012 | C60: =TEXT(ventasdiarias[[#This Row],[Fecha]],"dddd") -> lunes | D60: 24.4 | E60: 21.2 | F60: 0 | G60: 780 | H60: 10 | I60: 0 | J60: 0 | K60: =ventasdiarias[[#This Row],[Venta $]]+ventasdiarias[[#This Row],[Zelle $]]+(IF(ventasdiarias[[#This Row],[Tasa]]>0,(ventasdiarias[[#This Row],[punto]]+ventasdiarias[[#This Row],[Pago Movil]]+ventasdiarias[[#This Row],[Bs efecitivo]])/ventasdiarias[[#This Row],[Tasa]],"0")) -> 41.967213
B61: 45011 | C61: =TEXT(ventasdiarias[[#This Row],[Fecha]],"dddd") -> domingo | D61: 24.4 | K61: =ventasdiarias[[#This Row],[Venta $]]+ventasdiarias[[#This Row],[Zelle $]]+(IF(ventasdiarias[[#This Row],[Tasa]]>0,(ventasdiarias[[#This Row],[punto]]+ventasdiarias[[#This Row],[Pago Movil]]+ventasdiarias[[#This Row],[Bs efecitivo]])/ventasdiarias[[#This Row],[Tasa]],"0")) -> 0
B62: 45010 | C62: =TEXT(ventasdiarias[[#This Row],[Fecha]],"dddd") -> sábado | D62: 24.3 | E62: 113.41 | F62: 0 | G62: 0 | H62: 215 | I62: 0 | J62: 0 | K62: =ventasdiarias[[#This Row],[Venta $]]+ventasdiarias[[#This Row],[Zelle $]]+(IF(ventasdiarias[[#This Row],[Tasa]]>0,(ventasdiarias[[#This Row],[punto]]+ventasdiarias[[#This Row],[Pago Movil]]+ventasdiarias[[#This Row],[Bs efecitivo]])/ventasdiarias[[#This Row],[Tasa]],"0")) -> 215
B63: 45009 | C63: =TEXT(ventasdiarias[[#This Row],[Fecha]],"dddd") -> viernes | D63: 24.3 | E63: 46.568 | F63: 0 | G63: 0 | H63: 152 | I63: 0 | J63: 0 | K63: =ventasdiarias[[#This Row],[Venta $]]+ventasdiarias[[#This Row],[Zelle $]]+(IF(ventasdiarias[[#This Row],[Tasa]]>0,(ventasdiarias[[#This Row],[punto]]+ventasdiarias[[#This Row],[Pago Movil]]+ventasdiarias[[#This Row],[Bs efecitivo]])/ventasdiarias[[#This Row],[Tasa]],"0")) -> 152
B64: 45008 | C64: =TEXT(ventasdiarias[[#This Row],[Fecha]],"dddd") -> jueves | D64: 24.3 | K64: =ventasdiarias[[#This Row],[Venta $]]+ventasdiarias[[#This Row],[Zelle $]]+(IF(ventasdiarias[[#This Row],[Tasa]]>0,(ventasdiarias[[#This Row],[punto]]+ventasdiarias[[#This Row],[Pago Movil]]+ventasdiarias[[#This Row],[Bs efecitivo]])/ventasdiarias[[#This Row],[Tasa]],"0")) -> 0
B65: 45007 | C65: =TEXT(ventasdiarias[[#This Row],[Fecha]],"dddd") -> miércoles | D65: 24.2 | E65: 2.88 | F65: 50 | G65: 0 | H65: 6 | I65: 0 | J65: 0 | K65: =ventasdiarias[[#This Row],[Venta $]]+ventasdiarias[[#This Row],[Zelle $]]+(IF(ventasdiarias[[#This Row],[Tasa]]>0,(ventasdiarias[[#This Row],[punto]]+ventasdiarias[[#This Row],[Pago Movil]]+ventasdiarias[[#This Row],[Bs efecitivo]])/ventasdiarias[[#This Row],[Tasa]],"0")) -> 8.0661157
B66: 45006 | C66: =TEXT(ventasdiarias[[#This Row],[Fecha]],"dddd") -> martes | D66: 24.2 | E66: 8.35 | H66: 30 | K66: =ventasdiarias[[#This Row],[Venta $]]+ventasdiarias[[#This Row],[Zelle $]]+(IF(ventasdiarias[[#This Row],[Tasa]]>0,(ventasdiarias[[#This Row],[punto]]+ventasdiarias[[#This Row],[Pago Movil]]+ventasdiarias[[#This Row],[Bs efecitivo]])/ventasdiarias[[#This Row],[Tasa]],"0")) -> 30
B67: 45005 | C67: =TEXT(ventasdiarias[[#This Row],[Fecha]],"dddd") -> lunes | D67: 24.2 | E67: 36.8 | F67: 50 | G67: 242 | H67: 58 | I67: 0 | J67: 121 | K67: =ventasdiarias[[#This Row],[Venta $]]+ventasdiarias[[#This Row],[Zelle $]]+(IF(ventasdiarias[[#This Row],[Tasa]]>0,(ventasdiarias[[#This Row],[punto]]+ventasdiarias[[#This Row],[Pago Movil]]+ventasdiarias[[#This Row],[Bs efecitivo]])/ventasdiarias[[#This Row],[Tasa]],"0")) -> 75.066116
B68: 45003 | C68: =TEXT(ventasdiarias[[#This Row],[Fecha]],"dddd") -> sábado | D68: 24.06 | E68: 9.6 | H68: 20 | K68: =ventasdiarias[[#This Row],[Venta $]]+ventasdiarias[[#This Row],[Zelle $]]+(IF(ventasdiarias[[#This Row],[Tasa]]>0,(ventasdiarias[[#This Row],[punto]]+ventasdiarias[[#This Row],[Pago Movil]]+ventasdiarias[[#This Row],[Bs efecitivo]])/ventasdiarias[[#This Row],[Tasa]],"0")) -> 20
B69: 45002 | C69: =TEXT(ventasdiarias[[#This Row],[Fecha]],"dddd") -> viernes | D69: 24.06 | K69: =ventasdiarias[[#This Row],[Venta $]]+ventasdiarias[[#This Row],[Zelle $]]+(IF(ventasdiarias[[#This Row],[Tasa]]>0,(ventasdiarias[[#This Row],[punto]]+ventasdiarias[[#This Row],[Pago Movil]]+ventasdiarias[[#This Row],[Bs efecitivo]])/ventasdiarias[[#This Row],[Tasa]],"0")) -> 0
B70: 45001 | C70: =TEXT(ventasdiarias[[#This Row],[Fecha]],"dddd") -> jueves | D70: 24.06 | E70: 39.03 | F70: 120 | G70: 0 | H70: 75 | I70: 0 | J70: 360.07 | K70: =ventasdiarias[[#This Row],[Venta $]]+ventasdiarias[[#This Row],[Zelle $]]+(IF(ventasdiarias[[#This Row],[Tasa]]>0,(ventasdiarias[[#This Row],[punto]]+ventasdiarias[[#This Row],[Pago Movil]]+ventasdiarias[[#This Row],[Bs efecitivo]])/ventasdiarias[[#This Row],[Tasa]],"0")) -> 94.953034
B71: 45000 | C71: =TEXT(ventasdiarias[[#This Row],[Fecha]],"dddd") -> miércoles | D71: 24.06 | E71: 60.26 | H71: 115 | K71: =ventasdiarias[[#This Row],[Venta $]]+ventasdiarias[[#This Row],[Zelle $]]+(IF(ventasdiarias[[#This Row],[Tasa]]>0,(ventasdiarias[[#This Row],[punto]]+ventasdiarias[[#This Row],[Pago Movil]]+ventasdiarias[[#This Row],[Bs efecitivo]])/ventasdiarias[[#This Row],[Tasa]],"0")) -> 115
B72: 44999 | C72: =TEXT(ventasdiarias[[#This Row],[Fecha]],"dddd") -> martes | D72: 24.14 | E72: 32.45 | H72: 70 | K72: =ventasdiarias[[#This Row],[Venta $]]+ventasdiarias[[#This Row],[Zelle $]]+(IF(ventasdiarias[[#This Row],[Tasa]]>0,(ventasdiarias[[#This Row],[punto]]+ventasdiarias[[#This Row],[Pago Movil]]+ventasdiarias[[#This Row],[Bs efecitivo]])/ventasdiarias[[#This Row],[Tasa]],"0")) -> 70
B73: 44998 | C73: =TEXT(ventasdiarias[[#This Row],[Fecha]],"dddd") -> lunes | D73: 24.14 | E73: 31.9 | F73: 0 | G73: 0 | H73: 68 | I73: 0 | J73: 0 | K73: =ventasdiarias[[#This Row],[Venta $]]+ventasdiarias[[#This Row],[Zelle $]]+(IF(ventasdiarias[[#This Row],[Tasa]]>0,(ventasdiarias[[#This Row],[punto]]+ventasdiarias[[#This Row],[Pago Movil]]+ventasdiarias[[#This Row],[Bs efecitivo]])/ventasdiarias[[#This Row],[Tasa]],"0")) -> 68
B74: 44997 | C74: =TEXT(ventasdiarias[[#This Row],[Fecha]],"dddd") -> domingo | D74: 24.13 | K74: =ventasdiarias[[#This Row],[Venta $]]+ventasdiarias[[#This Row],[Zelle $]]+(IF(ventasdiarias[[#This Row],[Tasa]]>0,(ventasdiarias[[#This Row],[punto]]+ventasdiarias[[#This Row],[Pago Movil]]+ventasdiarias[[#This Row],[Bs efecitivo]])/ventasdiarias[[#This Row],[Tasa]],"0")) -> 0
B75: 44996 | C75: =TEXT(ventasdiarias[[#This Row],[Fecha]],"dddd") -> sábado | D75: 24.13 | E75: 51.79 | F75: 0 | G75: 0 | H75: 4 | I75: 70 | J75: 705.51 | K75: =ventasdiarias[[#This Row],[Venta $]]+ventasdiarias[[#This Row],[Zelle $]]+(IF(ventasdiarias[[#This Row],[Tasa]]>0,(ventasdiarias[[#This Row],[punto]]+ventasdiarias[[#This Row],[Pago Movil]]+ventasdiarias[[#This Row],[Bs efecitivo]])/ventasdiarias[[#This Row],[Tasa]],"0")) -> 103.23788
B76: 44995 | C76: =TEXT(ventasdiarias[[#This Row],[Fecha]],"dddd") -> viernes | D76: 24.13 | E76: 42.91 | F76: 0 | G76: 194.96 | H76: 97 | I76: 0 | J76: 0 | K76: =ventasdiarias[[#This Row],[Venta $]]+ventasdiarias[[#This Row],[Zelle $]]+(IF(ventasdiarias[[#This Row],[Tasa]]>0,(ventasdiarias[[#This Row],[punto]]+ventasdiarias[[#This Row],[Pago Movil]]+ventasdiarias[[#This Row],[Bs efecitivo]])/ventasdiarias[[#This Row],[Tasa]],"0")) -> 105.07957
B77: 44994 | C77: =TEXT(ventasdiarias[[#This Row],[Fecha]],"dddd") -> jueves | D77: 24.16 | E77: 14.25 | H77: 27 | K77: =ventasdiarias[[#This Row],[Venta $]]+ventasdiarias[[#This Row],[Zelle $]]+(IF(ventasdiarias[[#This Row],[Tasa]]>0,(ventasdiarias[[#This Row],[punto]]+ventasdiarias[[#This Row],[Pago Movil]]+ventasdiarias[[#This Row],[Bs efecitivo]])/ventasdiarias[[#This Row],[Tasa]],"0")) -> 27
B78: 44993 | C78: =TEXT(ventasdiarias[[#This Row],[Fecha]],"dddd") -> miércoles | D78: 24.15 | E78: 76.1 | H78: 155 | K78: =ventasdiarias[[#This Row],[Venta $]]+ventasdiarias[[#This Row],[Zelle $]]+(IF(ventasdiarias[[#This Row],[Tasa]]>0,(ventasdiarias[[#This Row],[punto]]+ventasdiarias[[#This Row],[Pago Movil]]+ventasdiarias[[#This Row],[Bs efecitivo]])/ventasdiarias[[#This Row],[Tasa]],"0")) -> 155
B79: 44992 | C79: =TEXT(ventasdiarias[[#This Row],[Fecha]],"dddd") -> martes | D79: 24.27 | E79: 79.38 | F79: 0 | G79: 0 | H79: 172 | I79: 0 | J79: 0 | K79: =ventasdiarias[[#This Row],[Venta $]]+ventasdiarias[[#This Row],[Zelle $]]+(IF(ventasdiarias[[#This Row],[Tasa]]>0,(ventasdiarias[[#This Row],[punto]]+ventasdiarias[[#This Row],[Pago Movil]]+ventasdiarias[[#This Row],[Bs efecitivo]])/ventasdiarias[[#This Row],[Tasa]],"0")) -> 172
B80: 44991 | C80: =TEXT(ventasdiarias[[#This Row],[Fecha]],"dddd") -> lunes | D80: 24.31 | E80: 29.22 | F80: 0 | G80: 0 | H80: 25 | I80: 0 | J80: 828.24 | K80: =ventasdiarias[[#This Row],[Venta $]]+ventasdiarias[[#This Row],[Zelle $]]+(IF(ventasdiarias[[#This Row],[Tasa]]>0,(ventasdiarias[[#This Row],[punto]]+ventasdiarias[[#This Row],[Pago Movil]]+ventasdiarias[[#This Row],[Bs efecitivo]])/ventasdiarias[[#This Row],[Tasa]],"0")) -> 59.06993
B81: 44990 | C81: =TEXT(ventasdiarias[[#This Row],[Fecha]],"dddd") -> domingo | D81: 24.35 | K81: =ventasdiarias[[#This Row],[Venta $]]+ventasdiarias[[#This Row],[Zelle $]]+(IF(ventasdiarias[[#This Row],[Tasa]]>0,(ventasdiarias[[#This Row],[punto]]+ventasdiarias[[#This Row],[Pago Movil]]+ventasdiarias[[#This Row],[Bs efecitivo]])/ventasdiarias[[#This Row],[Tasa]],"0")) -> 0
B82: 44989 | C82: =TEXT(ventasdiarias[[#This Row],[Fecha]],"dddd") -> sábado | D82: 24.35 | E82: 11.62 | F82: 0 | G82: 411.3 | H82: 10 | I82: 0 | J82: 0 | K82: =ventasdiarias[[#This Row],[Venta $]]+ventasdiarias[[#This Row],[Zelle $]]+(IF(ventasdiarias[[#This Row],[Tasa]]>0,(ventasdiarias[[#This Row],[punto]]+ventasdiarias[[#This Row],[Pago Movil]]+ventasdiarias[[#This Row],[Bs efecitivo]])/ventasdiarias[[#This Row],[Tasa]],"0")) -> 26.89117
B83: 44988 | C83: =TEXT(ventasdiarias[[#This Row],[Fecha]],"dddd") -> viernes | D83: 24.35 | E83: 164.55 | F83: 0 | G83: 0 | H83: 260.84 | I83: 0 | J83: 682.36 | K83: =ventasdiarias[[#This Row],[Venta $]]+ventasdiarias[[#This Row],[Zelle $]]+(IF(ventasdiarias[[#This Row],[Tasa]]>0,(ventasdiarias[[#This Row],[punto]]+ventasdiarias[[#This Row],[Pago Movil]]+ventasdiarias[[#This Row],[Bs efecitivo]])/ventasdiarias[[#This Row],[Tasa]],"0")) -> 288.863
B84: 44987 | C84: =TEXT(ventasdiarias[[#This Row],[Fecha]],"dddd") -> jueves | D84: 24.35 | E84: 1.5 | F84: 0 | G84: 0 | H84: 0 | I84: 0 | J84: 73.11 | K84: =ventasdiarias[[#This Row],[Venta $]]+ventasdiarias[[#This Row],[Zelle $]]+(IF(ventasdiarias[[#This Row],[Tasa]]>0,(ventasdiarias[[#This Row],[punto]]+ventasdiarias[[#This Row],[Pago Movil]]+ventasdiarias[[#This Row],[Bs efecitivo]])/ventasdiarias[[#This Row],[Tasa]],"0")) -> 3.0024641
B85: 44986 | C85: =TEXT(ventasdiarias[[#This Row],[Fecha]],"dddd") -> miércoles | D85: 24.36 | E85: 100.43 | F85: 0 | G85: 0 | H85: 171 | I85: 0 | J85: 608.4 | K85: =ventasdiarias[[#This Row],[Venta $]]+ventasdiarias[[#This Row],[Zelle $]]+(IF(ventasdiarias[[#This Row],[Tasa]]>0,(ventasdiarias[[#This Row],[punto]]+ventasdiarias[[#This Row],[Pago Movil]]+ventasdiarias[[#This Row],[Bs efecitivo]])/ventasdiarias[[#This Row],[Tasa]],"0")) -> 195.97537
B86: 44957 | C86: =TEXT(ventasdiarias[[#This Row],[Fecha]],"dddd") -> martes | E86: -8.83 | H86: -18 | K86: =ventasdiarias[[#This Row],[Venta $]]+ventasdiarias[[#This Row],[Zelle $]]+(IF(ventasdiarias[[#This Row],[Tasa]]>0,(ventasdiarias[[#This Row],[punto]]+ventasdiarias[[#This Row],[Pago Movil]]+ventasdiarias[[#This Row],[Bs efecitivo]])/ventasdiarias[[#This Row],[Tasa]],"0")) -> -18
B87: 44957 | C87: =TEXT(ventasdiarias[[#This Row],[Fecha]],"dddd") -> martes | D87: 21.95 | E87: 172.94 | G87: 236.62 | H87: 238 | J87: 236.62 | K87: =ventasdiarias[[#This Row],[Venta $]]+ventasdiarias[[#This Row],[Zelle $]]+(IF(ventasdiarias[[#This Row],[Tasa]]>0,(ventasdiarias[[#This Row],[punto]]+ventasdiarias[[#This Row],[Pago Movil]]+ventasdiarias[[#This Row],[Bs efecitivo]])/ventasdiarias[[#This Row],[Tasa]],"0")) -> 259.55991
B88: 44956 | C88: =TEXT(ventasdiarias[[#This Row],[Fecha]],"dddd") -> lunes | D88: 21.96 | E88: 163.66 | G88: 153 | H88: 232 | J88: 153 | K88: =ventasdiarias[[#This Row],[Venta $]]+ventasdiarias[[#This Row],[Zelle $]]+(IF(ventasdiarias[[#This Row],[Tasa]]>0,(ventasdiarias[[#This Row],[punto]]+ventasdiarias[[#This Row],[Pago Movil]]+ventasdiarias[[#This Row],[Bs efecitivo]])/ventasdiarias[[#This Row],[Tasa]],"0")) -> 245.93443
B89: 44954 | C89: =TEXT(ventasdiarias[[#This Row],[Fecha]],"dddd") -> sábado | D89: 21.72 | E89: 9.78 | H89: 19 | K89: =ventasdiarias[[#This Row],[Venta $]]+ventasdiarias[[#This Row],[Zelle $]]+(IF(ventasdiarias[[#This Row],[Tasa]]>0,(ventasdiarias[[#This Row],[punto]]+ventasdiarias[[#This Row],[Pago Movil]]+ventasdiarias[[#This Row],[Bs efecitivo]])/ventasdiarias[[#This Row],[Tasa]],"0")) -> 19
B90: 44953 | C90: =TEXT(ventasdiarias[[#This Row],[Fecha]],"dddd") -> viernes | D90: 21.72 | E90: 69.66 | G90: 695.04 | H90: 98 | J90: 695.04 | K90: =ventasdiarias[[#This Row],[Venta $]]+ventasdiarias[[#This Row],[Zelle $]]+(IF(ventasdiarias[[#This Row],[Tasa]]>0,(ventasdiarias[[#This Row],[punto]]+ventasdiarias[[#This Row],[Pago Movil]]+ventasdiarias[[#This Row],[Bs efecitivo]])/ventasdiarias[[#This Row],[Tasa]],"0")) -> 162
B91: 44952 | C91: =TEXT(ventasdiarias[[#This Row],[Fecha]],"dddd") -> jueves | D91: 21.31 | E91: -3 | G91: -17.35 | H91: -5 | J91: -17.35 | K91: =ventasdiarias[[#This Row],[Venta $]]+ventasdiarias[[#This Row],[Zelle $]]+(IF(ventasdiarias[[#This Row],[Tasa]]>0,(ventasdiarias[[#This Row],[punto]]+ventasdiarias[[#This Row],[Pago Movil]]+ventasdiarias[[#This Row],[Bs efecitivo]])/ventasdiarias[[#This Row],[Tasa]],"0")) -> -6.6283435
B92: 44952 | C92: =TEXT(ventasdiarias[[#This Row],[Fecha]],"dddd") -> jueves | D92: 21.31 | E92: 11.81 | G92: 213.1 | H92: 14 | J92: 213.1 | K92: =ventasdiarias[[#This Row],[Venta $]]+ventasdiarias[[#This Row],[Zelle $]]+(IF(ventasdiarias[[#This Row],[Tasa]]>0,(ventasdiarias[[#This Row],[punto]]+ventasdiarias[[#This Row],[Pago Movil]]+ventasdiarias[[#This Row],[Bs efecitivo]])/ventasdiarias[[#This Row],[Tasa]],"0")) -> 34
B93: 44951 | C93: =TEXT(ventasdiarias[[#This Row],[Fecha]],"dddd") -> miércoles | D93: 21.17 | E93: 68.4 | G93: 225 | H93: 106 | J93: 225 | K93: =ventasdiarias[[#This Row],[Venta $]]+ventasdiarias[[#This Row],[Zelle $]]+(IF(ventasdiarias[[#This Row],[Tasa]]>0,(ventasdiarias[[#This Row],[punto]]+ventasdiarias[[#This Row],[Pago Movil]]+ventasdiarias[[#This Row],[Bs efecitivo]])/ventasdiarias[[#This Row],[Tasa]],"0")) -> 127.2565
B94: 44950 | C94: =TEXT(ventasdiarias[[#This Row],[Fecha]],"dddd") -> martes | D94: 20.73 | E94: 52.98 | G94: 891.39 | H94: 81 | J94: 891.39 | K94: =ventasdiarias[[#This Row],[Venta $]]+ventasdiarias[[#This Row],[Zelle $]]+(IF(ventasdiarias[[#This Row],[Tasa]]>0,(ventasdiarias[[#This Row],[punto]]+ventasdiarias[[#This Row],[Pago Movil]]+ventasdiarias[[#This Row],[Bs efecitivo]])/ventasdiarias[[#This Row],[Tasa]],"0")) -> 167
B95: 44949 | C95: =TEXT(ventasdiarias[[#This Row],[Fecha]],"dddd") -> lunes | D95: 20.52 | E95: 7.68 | G95: =9.87*ventasdiarias[[#This Row],[Tasa]] -> 202.5324 | H95: 14 | J95: =9.87*ventasdiarias[[#This Row],[Tasa]] -> 202.5324 | K95: =ventasdiarias[[#This Row],[Venta $]]+ventasdiarias[[#This Row],[Zelle $]]+(IF(ventasdiarias[[#This Row],[Tasa]]>0,(ventasdiarias[[#This Row],[punto]]+ventasdiarias[[#This Row],[Pago Movil]]+ventasdiarias[[#This Row],[Bs efecitivo]])/ventasdiarias[[#This Row],[Tasa]],"0")) -> 33.74
B96: 44947 | C96: =TEXT(ventasdiarias[[#This Row],[Fecha]],"dddd") -> sábado | D96: 20.52 | E96: 169.27 | G96: =128*ventasdiarias[[#This Row],[Tasa]] -> 2626.56 | H96: 206.4 | J96: =128*ventasdiarias[[#This Row],[Tasa]] -> 2626.56 | K96: =ventasdiarias[[#This Row],[Venta $]]+ventasdiarias[[#This Row],[Zelle $]]+(IF(ventasdiarias[[#This Row],[Tasa]]>0,(ventasdiarias[[#This Row],[punto]]+ventasdiarias[[#This Row],[Pago Movil]]+ventasdiarias[[#This Row],[Bs efecitivo]])/ventasdiarias[[#This Row],[Tasa]],"0")) -> 462.4
B97: 44946 | C97: =TEXT(ventasdiarias[[#This Row],[Fecha]],"dddd") -> viernes | D97: 20.29 | E97: 8.36 | G97: 405.8 | J97: 405.8 | K97: =ventasdiarias[[#This Row],[Venta $]]+ventasdiarias[[#This Row],[Zelle $]]+(IF(ventasdiarias[[#This Row],[Tasa]]>0,(ventasdiarias[[#This Row],[punto]]+ventasdiarias[[#This Row],[Pago Movil]]+ventasdiarias[[#This Row],[Bs efecitivo]])/ventasdiarias[[#This Row],[Tasa]],"0")) -> 40
B98: 44945 | C98: =TEXT(ventasdiarias[[#This Row],[Fecha]],"dddd") -> jueves | D98: 19.98 | E98: 87.74 | G98: 1205.58 | H98: 41 | I98: 57 | J98: 1205.58 | K98: =ventasdiarias[[#This Row],[Venta $]]+ventasdiarias[[#This Row],[Zelle $]]+(IF(ventasdiarias[[#This Row],[Tasa]]>0,(ventasdiarias[[#This Row],[punto]]+ventasdiarias[[#This Row],[Pago Movil]]+ventasdiarias[[#This Row],[Bs efecitivo]])/ventasdiarias[[#This Row],[Tasa]],"0")) -> 218.67868
B99: 44944 | C99: =TEXT(ventasdiarias[[#This Row],[Fecha]],"dddd") -> miércoles | D99: 19.98 | E99: 70.45 | G99: 199.8 | H99: 70 | I99: 57.11 | J99: 199.8 | K99: =ventasdiarias[[#This Row],[Venta $]]+ventasdiarias[[#This Row],[Zelle $]]+(IF(ventasdiarias[[#This Row],[Tasa]]>0,(ventasdiarias[[#This Row],[punto]]+ventasdiarias[[#This Row],[Pago Movil]]+ventasdiarias[[#This Row],[Bs efecitivo]])/ventasdiarias[[#This Row],[Tasa]],"0")) -> 147.11
B100: 44943 | C100: =TEXT(ventasdiarias[[#This Row],[Fecha]],"dddd") -> martes | D100: 19.66 | E100: 44.61 | G100: 294.9 | H100: 77.25 | J100: 294.9 | K100: =ventasdiarias[[#This Row],[Venta $]]+ventasdiarias[[#This Row],[Zelle $]]+(IF(ventasdiarias[[#This Row],[Tasa]]>0,(ventasdiarias[[#This Row],[punto]]+ventasdiarias[[#This Row],[Pago Movil]]+ventasdiarias[[#This Row],[Bs efecitivo]])/ventasdiarias[[#This Row],[Tasa]],"0")) -> 107.25
B101: 44942 | C101: =TEXT(ventasdiarias[[#This Row],[Fecha]],"dddd") -> lunes | D101: 19.66 | E101: 85.48 | G101: 373.54 | H101: 160 | J101: 373.54 | K101: =ventasdiarias[[#This Row],[Venta $]]+ventasdiarias[[#This Row],[Zelle $]]+(IF(ventasdiarias[[#This Row],[Tasa]]>0,(ventasdiarias[[#This Row],[punto]]+ventasdiarias[[#This Row],[Pago Movil]]+ventasdiarias[[#This Row],[Bs efecitivo]])/ventasdiarias[[#This Row],[Tasa]],"0")) -> 198
B102: 44940 | C102: =TEXT(ventasdiarias[[#This Row],[Fecha]],"dddd") -> sábado | D102: 19.45 | E102: 25.55 | G102: 61.7 | H102: 47 | J102: 61.7 | K102: =ventasdiarias[[#This Row],[Venta $]]+ventasdiarias[[#This Row],[Zelle $]]+(IF(ventasdiarias[[#This Row],[Tasa]]>0,(ventasdiarias[[#This Row],[punto]]+ventasdiarias[[#This Row],[Pago Movil]]+ventasdiarias[[#This Row],[Bs efecitivo]])/ventasdiarias[[#This Row],[Tasa]],"0")) -> 53.344473
B103: 44939 | C103: =TEXT(ventasdiarias[[#This Row],[Fecha]],"dddd") -> viernes | D103: 19.28 | E103: 52.99 | G103: 404.88 | H103: 92.12 | J103: 404.88 | K103: =ventasdiarias[[#This Row],[Venta $]]+ventasdiarias[[#This Row],[Zelle $]]+(IF(ventasdiarias[[#This Row],[Tasa]]>0,(ventasdiarias[[#This Row],[punto]]+ventasdiarias[[#This Row],[Pago Movil]]+ventasdiarias[[#This Row],[Bs efecitivo]])/ventasdiarias[[#This Row],[Tasa]],"0")) -> 134.12
B104: 44938 | C104: =TEXT(ventasdiarias[[#This Row],[Fecha]],"dddd") -> jueves | D104: 19.28 | E104: 14.52 | G104: 115.68 | H104: 25.4 | J104: 115.68 | K104: =ventasdiarias[[#This Row],[Venta $]]+ventasdiarias[[#This Row],[Zelle $]]+(IF(ventasdiarias[[#This Row],[Tasa]]>0,(ventasdiarias[[#This Row],[punto]]+ventasdiarias[[#This Row],[Pago Movil]]+ventasdiarias[[#This Row],[Bs efecitivo]])/ventasdiarias[[#This Row],[Tasa]],"0")) -> 37.4
B105: 44937 | C105: =TEXT(ventasdiarias[[#This Row],[Fecha]],"dddd") -> miércoles | D105: 18.61 | E105: 64.12 | H105: 140 | K105: =ventasdiarias[[#This Row],[Venta $]]+ventasdiarias[[#This Row],[Zelle $]]+(IF(ventasdiarias[[#This Row],[Tasa]]>0,(ventasdiarias[[#This Row],[punto]]+ventasdiarias[[#This Row],[Pago Movil]]+ventasdiarias[[#This Row],[Bs efecitivo]])/ventasdiarias[[#This Row],[Tasa]],"0")) -> 140
B106: 44936 | C106: =TEXT(ventasdiarias[[#This Row],[Fecha]],"dddd") -> martes | D106: 18.61 | E106: 28.26 | H106: 78 | K106: =ventasdiarias[[#This Row],[Venta $]]+ventasdiarias[[#This Row],[Zelle $]]+(IF(ventasdiarias[[#This Row],[Tasa]]>0,(ventasdiarias[[#This Row],[punto]]+ventasdiarias[[#This Row],[Pago Movil]]+ventasdiarias[[#This Row],[Bs efecitivo]])/ventasdiarias[[#This Row],[Tasa]],"0")) -> 78
B107: 44935 | C107: =TEXT(ventasdiarias[[#This Row],[Fecha]],"dddd") -> lunes | D107: 18.61 | E107: 18.36 | G107: 130.27 | H107: 35 | J107: 130.27 | K107: =ventasdiarias[[#This Row],[Venta $]]+ventasdiarias[[#This Row],[Zelle $]]+(IF(ventasdiarias[[#This Row],[Tasa]]>0,(ventasdiarias[[#This Row],[punto]]+ventasdiarias[[#This Row],[Pago Movil]]+ventasdiarias[[#This Row],[Bs efecitivo]])/ventasdiarias[[#This Row],[Tasa]],"0")) -> 49
B108: 44926 | C108: =TEXT(ventasdiarias[[#This Row],[Fecha]],"dddd") -> sábado | D108: 17.49 | E108: 25.69 | H108: 40 | K108: =ventasdiarias[[#This Row],[Venta $]]+ventasdiarias[[#This Row],[Zelle $]]+(IF(ventasdiarias[[#This Row],[Tasa]]>0,(ventasdiarias[[#This Row],[punto]]+ventasdiarias[[#This Row],[Pago Movil]]+ventasdiarias[[#This Row],[Bs efecitivo]])/ventasdiarias[[#This Row],[Tasa]],"0")) -> 40
B109: 44925 | C109: =TEXT(ventasdiarias[[#This Row],[Fecha]],"dddd") -> viernes | D109: 17.28 | E109: 85.86 | G109: 1399.68 | H109: 120 | J109: 1399.68 | K109: =ventasdiarias[[#This Row],[Venta $]]+ventasdiarias[[#This Row],[Zelle $]]+(IF(ventasdiarias[[#This Row],[Tasa]]>0,(ventasdiarias[[#This Row],[punto]]+ventasdiarias[[#This Row],[Pago Movil]]+ventasdiarias[[#This Row],[Bs efecitivo]])/ventasdiarias[[#This Row],[Tasa]],"0")) -> 282
B110: 44924 | C110: =TEXT(ventasdiarias[[#This Row],[Fecha]],"dddd") -> jueves | D110: 17.11 | E110: 69.97 | G110: 2095.42 | H110: 35 | J110: 2095.42 | K110: =ventasdiarias[[#This Row],[Venta $]]+ventasdiarias[[#This Row],[Zelle $]]+(IF(ventasdiarias[[#This Row],[Tasa]]>0,(ventasdiarias[[#This Row],[punto]]+ventasdiarias[[#This Row],[Pago Movil]]+ventasdiarias[[#This Row],[Bs efecitivo]])/ventasdiarias[[#This Row],[Tasa]],"0")) -> 279.93513
B111: 44923 | C111: =TEXT(ventasdiarias[[#This Row],[Fecha]],"dddd") -> miércoles | D111: 16.8 | E111: 99.63 | G111: 1027.152 | H111: 152 | J111: 1027.152 | K111: =ventasdiarias[[#This Row],[Venta $]]+ventasdiarias[[#This Row],[Zelle $]]+(IF(ventasdiarias[[#This Row],[Tasa]]>0,(ventasdiarias[[#This Row],[punto]]+ventasdiarias[[#This Row],[Pago Movil]]+ventasdiarias[[#This Row],[Bs efecitivo]])/ventasdiarias[[#This Row],[Tasa]],"0")) -> 274.28
B112: 44922 | C112: =TEXT(ventasdiarias[[#This Row],[Fecha]],"dddd") -> martes | D112: 16.57 | E112: 130.96 | G112: 251.5 | H112: 148 | J112: 251.5 | K112: =ventasdiarias[[#This Row],[Venta $]]+ventasdiarias[[#This Row],[Zelle $]]+(IF(ventasdiarias[[#This Row],[Tasa]]>0,(ventasdiarias[[#This Row],[punto]]+ventasdiarias[[#This Row],[Pago Movil]]+ventasdiarias[[#This Row],[Bs efecitivo]])/ventasdiarias[[#This Row],[Tasa]],"0")) -> 178.35607
...

Sheet Gastos F-E
A2: TOTAL FIJOS | B2: EVENTUALES | C2: RETIRADO | D2: Comisiones | E2: TOTAL
A3: =SUMIFS(gastoseventuales[MONTO TOTAL EN DOLARES],gastoseventuales[FECHA],">="&DATE(Resumen!$C$2,Resumen!$B$2,1),gastoseventuales[FECHA],"<="&EOMONTH(DATE(Resumen!$C$2,Resumen!$B$2,1),0),gastoseventuales[GASTO],"FIJO") -> 631.25 | B3: =SUMIFS(gastoseventuales[MONTO TOTAL EN DOLARES],gastoseventuales[FECHA],">="&DATE(Resumen!$C$2,Resumen!$B$2,1),gastoseventuales[FECHA],"<="&EOMONTH(DATE(Resumen!$C$2,Resumen!$B$2,1),0),gastoseventuales[GASTO],"EVENTUAL") -> 302.14238 | C3: =SUMIFS(gastoseventuales[MONTO TOTAL EN DOLARES],gastoseventuales[FECHA],">="&DATE(Resumen!$C$2,Resumen!$B$2,1),gastoseventuales[FECHA],"<="&EOMONTH(DATE(Resumen!$C$2,Resumen!$B$2,1),0),gastoseventuales[GASTO],"RETIRADO") -> 120 | D3: =SUMIFS(gastoseventuales[MONTO TOTAL EN DOLARES],gastoseventuales[FECHA],">="&DATE(Resumen!$C$2,Resumen!$B$2,1),gastoseventuales[FECHA],"<="&EOMONTH(DATE(Resumen!$C$2,Resumen!$B$2,1),0),gastoseventuales[GASTO],"COMISION") -> 0 | E3: =SUMIFS(gastoseventuales[MONTO TOTAL EN DOLARES],gastoseventuales[FECHA],">="&DATE(Resumen!C2,Resumen!B2,1),gastoseventuales[FECHA],"<="&EOMONTH(DATE(Resumen!C2,Resumen!B2,1),0)) -> 1053.3924
A7: GASTOS FIJOS | B7: FECHAS/PAGOS | C7: ESTADO | D7: MONTO | F7: DESCRIPCIÓN | G7: FECHA | H7: GASTO | I7: TASA | J7: BS | K7: DOLARES | L7: MONTO TOTAL EN DOLARES
A8: DIVA ACTIVIDAD ECONOMICA | B8: 10-MENSUAL | C8: EN DEUDA | D8: 13.69 | F8: Nomina ultimo | G8: 45077 | H8: FIJO | I8: =VLOOKUP(gastoseventuales[[#This Row],[FECHA]],ventasdiarias[],3,FALSE) -> 26.16 | J8: 915.6 | K8: 40 | L8: =(gastoseventuales[[#This Row],[BS]]/gastoseventuales[[#This Row],[TASA]])+gastoseventuales[[#This Row],[DOLARES]] -> 75
A9: CANTV | B9: 10-MENSUAL | C9: EN DEUDA | F9: iva atrasado | G9: 45076 | H9: EVENTUAL | I9: =VLOOKUP(gastoseventuales[[#This Row],[FECHA]],ventasdiarias[],3,FALSE) -> 26.25 | J9: 3677.69 | L9: =(gastoseventuales[[#This Row],[BS]]/gastoseventuales[[#This Row],[TASA]])+gastoseventuales[[#This Row],[DOLARES]] -> 140.10248
A10: PAGO SENIAT (IVA) | B10: 15-30-SEMANAL | C10: EN DEUDA | D10: 20.84 | F10: entrgado a yhamil | G10: 45073 | H10: RETIRADO | I10: =VLOOKUP(gastoseventuales[[#This Row],[FECHA]],ventasdiarias[],3,FALSE) -> 26 | K10: 50 | L10: =(gastoseventuales[[#This Row],[BS]]/gastoseventuales[[#This Row],[TASA]])+gastoseventuales[[#This Row],[DOLARES]] -> 50
A11: NOMINA QUINCENAL | B11: 15-MENSUAL | C11: PAGADO | D11: 50 | F11: agua para el local | G11: 45071 | H11: EVENTUAL | I11: =VLOOKUP(gastoseventuales[[#This Row],[FECHA]],ventasdiarias[],3,FALSE) -> 26 | J11: 10 | L11: =(gastoseventuales[[#This Row],[BS]]/gastoseventuales[[#This Row],[TASA]])+gastoseventuales[[#This Row],[DOLARES]] -> 0.38461538
A12: ALQUILER LOCAL | B12: 15-MENSUAL | C12: EN DEUDA | D12: 500 | F12: sevicio para la moto | G12: 45070 | H12: EVENTUAL | I12: =VLOOKUP(gastoseventuales[[#This Row],[FECHA]],ventasdiarias[],3,FALSE) -> 26 | J12: 340 | L12: =(gastoseventuales[[#This Row],[BS]]/gastoseventuales[[#This Row],[TASA]])+gastoseventuales[[#This Row],[DOLARES]] -> 13.076923
A13: SERVICIO (ACTIVIDAD ECONOMICA) | B13: 30-MENSUAL | C13: EN DEUDA | D13: 2 | F13: adelanto para elton | G13: 45069 | H13: EVENTUAL | I13: =VLOOKUP(gastoseventuales[[#This Row],[FECHA]],ventasdiarias[],3,FALSE) -> 26 | J13: 20 | L13: =(gastoseventuales[[#This Row],[BS]]/gastoseventuales[[#This Row],[TASA]])+gastoseventuales[[#This Row],[DOLARES]] -> 0.76923077
A14: SEGURO SOCIAL | B14: 30-MENSUAL | C14: EN DEUDA | D14: 6.5 | F14: Entregado a Yhamil para el Jeep | G14: 45066 | H14: RETIRADO | I14: =VLOOKUP(gastoseventuales[[#This Row],[FECHA]],ventasdiarias[],3,FALSE) -> 25.9 | K14: 100 | L14: =(gastoseventuales[[#This Row],[BS]]/gastoseventuales[[#This Row],[TASA]])+gastoseventuales[[#This Row],[DOLARES]] -> 100
A15: NOMINA ULTIMO | B15: 30-MENSUAL | C15: EN DEUDA | D15: 75 | F15: Entregado a Yhamil | G15: 45064 | H15: RETIRADO | I15: =VLOOKUP(gastoseventuales[[#This Row],[FECHA]],ventasdiarias[],3,FALSE) -> 25.81 | K15: 15 | L15: =(gastoseventuales[[#This Row],[BS]]/gastoseventuales[[#This Row],[TASA]])+gastoseventuales[[#This Row],[DOLARES]] -> 15
A16: EDDIE | B16: 30-MENSUAL | C16: EN DEUDA | D16: 5 | F16: Entregado a Yhamil | G16: 45063 | H16: RETIRADO | I16: =VLOOKUP(gastoseventuales[[#This Row],[FECHA]],ventasdiarias[],3,FALSE) -> 25.64 | K16: 120 | L16: =(gastoseventuales[[#This Row],[BS]]/gastoseventuales[[#This Row],[TASA]])+gastoseventuales[[#This Row],[DOLARES]] -> 120
A17: CONTADORES | B17: 30-MENSUAL | C17: EN DEUDA | D17: 30 | F17: Quincena | G17: 45061 | H17: FIJO | I17: =VLOOKUP(gastoseventuales[[#This Row],[FECHA]],ventasdiarias[],3,FALSE) -> 25.43 | J17: 381.45 | K17: 60 | L17: =(gastoseventuales[[#This Row],[BS]]/gastoseventuales[[#This Row],[TASA]])+gastoseventuales[[#This Row],[DOLARES]] -> 75
A18: ASEO | B18: TRIMESTRAL | C18: EN DEUDA | F18: PAPEL TOILET | G18: 45061 | H18: EVENTUAL | I18: =VLOOKUP(gastoseventuales[[#This Row],[FECHA]],ventasdiarias[],3,FALSE) -> 25.43 | J18: 40 | L18: =(gastoseventuales[[#This Row],[BS]]/gastoseventuales[[#This Row],[TASA]])+gastoseventuales[[#This Row],[DOLARES]] -> 1.5729453
A19: LUZ | C19: EN DEUDA | D19: 2903.69 | F19: aceite para vehículo de Yhamil | G19: 45059 | H19: RETIRADO | I19: =VLOOKUP(gastoseventuales[[#This Row],[FECHA]],ventasdiarias[],3,FALSE) -> 25.17 | J19: 457.74 | L19: =(gastoseventuales[[#This Row],[BS]]/gastoseventuales[[#This Row],[TASA]])+gastoseventuales[[#This Row],[DOLARES]] -> 18.185936
A20: AGUA | C20: EN DEUDA | F20: pagado por consumo de yhamil | G20: 45059 | H20: RETIRADO | I20: =VLOOKUP(gastoseventuales[[#This Row],[FECHA]],ventasdiarias[],3,FALSE) -> 25.17 | K20: 40 | L20: =(gastoseventuales[[#This Row],[BS]]/gastoseventuales[[#This Row],[TASA]])+gastoseventuales[[#This Row],[DOLARES]] -> 40
A21: CONDOMINIO | B21: 15-MENSUAL | C21: EN DEUDA | D21: 15 | F21: Prestamo a Harley | G21: 45054 | H21: RETIRADO | I21: =VLOOKUP(gastoseventuales[[#This Row],[FECHA]],ventasdiarias[],3,FALSE) -> 25.5 | K21: 100 | L21: =(gastoseventuales[[#This Row],[BS]]/gastoseventuales[[#This Row],[TASA]])+gastoseventuales[[#This Row],[DOLARES]] -> 100
A22: MEGAFIBRA | B22: 15-MENSUAL | C22: PAGADO | D22: 40 | F22: Para Doña Por alquiler retrasado | G22: 45052 | H22: EVENTUAL | I22: =VLOOKUP(gastoseventuales[[#This Row],[FECHA]],ventasdiarias[],3,FALSE) -> 25.05 | K22: 500 | L22: =(gastoseventuales[[#This Row],[BS]]/gastoseventuales[[#This Row],[TASA]])+gastoseventuales[[#This Row],[DOLARES]] -> 500
A23: YHAMIL GOMEZ PADRE INTERESES | B23: 30-MENSUAL | C23: PAGADO | D23: 50 | F23: enviado a la doña | G23: 45052 | H23: EVENTUAL | I23: =VLOOKUP(gastoseventuales[[#This Row],[FECHA]],ventasdiarias[],3,FALSE) -> 25.05 | K23: 190 | L23: =(gastoseventuales[[#This Row],[BS]]/gastoseventuales[[#This Row],[TASA]])+gastoseventuales[[#This Row],[DOLARES]] -> 190
A24: CANTV (APARTMENTO YHAMIL) | B24: 10-MENSUAL | C24: PAGADO | F24: Alquiler | G24: 45046 | H24: FIJO | I24: =VLOOKUP(gastoseventuales[[#This Row],[FECHA]],ventasdiarias[],3,FALSE) -> 24.71 | K24: 500 | L24: =(gastoseventuales[[#This Row],[BS]]/gastoseventuales[[#This Row],[TASA]])+gastoseventuales[[#This Row],[DOLARES]] -> 500
F25: NOMINA ULTIMO | G25: 45046 | H25: FIJO | I25: =VLOOKUP(gastoseventuales[[#This Row],[FECHA]],ventasdiarias[],3,FALSE) -> 24.71 | J25: 370.65 | K25: 60 | L25: =(gastoseventuales[[#This Row],[BS]]/gastoseventuales[[#This Row],[TASA]])+gastoseventuales[[#This Row],[DOLARES]] -> 75
F26: intereses señor yhamil | G26: 45046 | H26: FIJO | I26: =VLOOKUP(gastoseventuales[[#This Row],[FECHA]],ventasdiarias[],3,FALSE) -> 24.71 | K26: 50 | L26: =(gastoseventuales[[#This Row],[BS]]/gastoseventuales[[#This Row],[TASA]])+gastoseventuales[[#This Row],[DOLARES]] -> 50
F27: Entregado a Yhamil | G27: 45040 | H27: RETIRADO | I27: =VLOOKUP(gastoseventuales[[#This Row],[FECHA]],ventasdiarias[],3,FALSE) -> 24.67 | K27: 500 | L27: =(gastoseventuales[[#This Row],[BS]]/gastoseventuales[[#This Row],[TASA]])+gastoseventuales[[#This Row],[DOLARES]] -> 500
F28: Pago Gato publicidad | G28: 45038 | H28: EVENTUAL | I28: =VLOOKUP(gastoseventuales[[#This Row],[FECHA]],ventasdiarias[],3,FALSE) -> 24.57 | K28: 40 | L28: =(gastoseventuales[[#This Row],[BS]]/gastoseventuales[[#This Row],[TASA]])+gastoseventuales[[#This Row],[DOLARES]] -> 40
F29: Entregado a Yhamil | G29: 45034 | H29: RETIRADO | I29: =VLOOKUP(gastoseventuales[[#This Row],[FECHA]],ventasdiarias[],3,FALSE) -> 24.56 | K29: 60 | L29: =(gastoseventuales[[#This Row],[BS]]/gastoseventuales[[#This Row],[TASA]])+gastoseventuales[[#This Row],[DOLARES]] -> 60
F30: prestamo a replay | G30: 45033 | H30: RETIRADO | I30: =VLOOKUP(gastoseventuales[[#This Row],[FECHA]],ventasdiarias[],3,FALSE) -> 24.57 | K30: 200 | L30: =(gastoseventuales[[#This Row],[BS]]/gastoseventuales[[#This Row],[TASA]])+gastoseventuales[[#This Row],[DOLARES]] -> 200
F31: contadores | G31: 45033 | H31: fijo | I31: =VLOOKUP(gastoseventuales[[#This Row],[FECHA]],ventasdiarias[],3,FALSE) -> 24.57 | K31: 30 | L31: =(gastoseventuales[[#This Row],[BS]]/gastoseventuales[[#This Row],[TASA]])+gastoseventuales[[#This Row],[DOLARES]] -> 30
F32: actividad economica | G32: 45033 | H32: FIJO | I32: =VLOOKUP(gastoseventuales[[#This Row],[FECHA]],ventasdiarias[],3,FALSE) -> 24.57 | K32: 23 | L32: =(gastoseventuales[[#This Row],[BS]]/gastoseventuales[[#This Row],[TASA]])+gastoseventuales[[#This Row],[DOLARES]] -> 23
F33: SERVICIO (Actividad economica) | G33: 45033 | H33: fijo | I33: =VLOOKUP(gastoseventuales[[#This Row],[FECHA]],ventasdiarias[],3,FALSE) -> 24.57 | K33: 2 | L33: =(gastoseventuales[[#This Row],[BS]]/gastoseventuales[[#This Row],[TASA]])+gastoseventuales[[#This Row],[DOLARES]] -> 2
F34: NOMINA QUINCENAL | G34: 45031 | H34: fijo | I34: =VLOOKUP(gastoseventuales[[#This Row],[FECHA]],ventasdiarias[],3,FALSE) -> 24.54 | J34: 368.1 | K34: 60 | L34: =(gastoseventuales[[#This Row],[BS]]/gastoseventuales[[#This Row],[TASA]])+gastoseventuales[[#This Row],[DOLARES]] -> 75
F35: MEGAFIBRA | G35: 45029 | H35: fijo | I35: =VLOOKUP(gastoseventuales[[#This Row],[FECHA]],ventasdiarias[],3,FALSE) -> 24.48 | K35: 40 | L35: =(gastoseventuales[[#This Row],[BS]]/gastoseventuales[[#This Row],[TASA]])+gastoseventuales[[#This Row],[DOLARES]] -> 40
F36: pago de viveres a la zona | G36: 45029 | H36: RETIRADO | I36: =VLOOKUP(gastoseventuales[[#This Row],[FECHA]],ventasdiarias[],3,FALSE) -> 24.48 | K36: 49 | L36: =(gastoseventuales[[#This Row],[BS]]/gastoseventuales[[#This Row],[TASA]])+gastoseventuales[[#This Row],[DOLARES]] -> 49
F37: renovacion patentes | G37: 45029 | H37: EVENTUAL | I37: =VLOOKUP(gastoseventuales[[#This Row],[FECHA]],ventasdiarias[],3,FALSE) -> 24.48 | K37: 20 | L37: =(gastoseventuales[[#This Row],[BS]]/gastoseventuales[[#This Row],[TASA]])+gastoseventuales[[#This Row],[DOLARES]] -> 20
F38: detergente | G38: 45021 | H38: EVENTUAL | I38: =VLOOKUP(gastoseventuales[[#This Row],[FECHA]],ventasdiarias[],3,FALSE) -> 24.44 | K38: 6 | L38: =(gastoseventuales[[#This Row],[BS]]/gastoseventuales[[#This Row],[TASA]])+gastoseventuales[[#This Row],[DOLARES]] -> 6
F39: nomina ultimo | G39: 45016 | H39: fijo | I39: =VLOOKUP(gastoseventuales[[#This Row],[FECHA]],ventasdiarias[],3,FALSE) -> 24.48 | J39: 367.2 | K39: 60 | L39: =(gastoseventuales[[#This Row],[BS]]/gastoseventuales[[#This Row],[TASA]])+gastoseventuales[[#This Row],[DOLARES]] -> 75
F40: Entregado a Yhamil | G40: 45016 | H40: RETIRADO | I40: =VLOOKUP(gastoseventuales[[#This Row],[FECHA]],ventasdiarias[],3,FALSE) -> 24.48 | K40: 100 | L40: =(gastoseventuales[[#This Row],[BS]]/gastoseventuales[[#This Row],[TASA]])+gastoseventuales[[#This Row],[DOLARES]] -> 100
F41: Alquiler local | G41: 45016 | H41: fijo | I41: =VLOOKUP(gastoseventuales[[#This Row],[FECHA]],ventasdiarias[],3,FALSE) -> 24.48 | K41: 500 | L41: =(gastoseventuales[[#This Row],[BS]]/gastoseventuales[[#This Row],[TASA]])+gastoseventuales[[#This Row],[DOLARES]] -> 500
F42: cantv | G42: 45016 | H42: fijo | I42: =VLOOKUP(gastoseventuales[[#This Row],[FECHA]],ventasdiarias[],3,FALSE) -> 24.48 | J42: 153 | L42: =(gastoseventuales[[#This Row],[BS]]/gastoseventuales[[#This Row],[TASA]])+gastoseventuales[[#This Row],[DOLARES]] -> 6.25
F43: Gabriela Spacabento | G43: 45010 | H43: EVENTUAL | I43: =VLOOKUP(gastoseventuales[[#This Row],[FECHA]],ventasdiarias[],3,FALSE) -> 24.3 | K43: 120 | L43: =(gastoseventuales[[#This Row],[BS]]/gastoseventuales[[#This Row],[TASA]])+gastoseventuales[[#This Row],[DOLARES]] -> 120
G44: 45010 | H44: EVENTUAL | I44: =VLOOKUP(gastoseventuales[[#This Row],[FECHA]],ventasdiarias[],3,FALSE) -> 24.3 | J44: 46 | L44: =(gastoseventuales[[#This Row],[BS]]/gastoseventuales[[#This Row],[TASA]])+gastoseventuales[[#This Row],[DOLARES]] -> 1.8930041
F45: publicidad | G45: 45002 | H45: EVENTUAL | I45: =VLOOKUP(gastoseventuales[[#This Row],[FECHA]],ventasdiarias[],3,FALSE) -> 24.06 | K45: 20 | L45: =(gastoseventuales[[#This Row],[BS]]/gastoseventuales[[#This Row],[TASA]])+gastoseventuales[[#This Row],[DOLARES]] -> 20
F46: Nómina quincenal | G46: 45001 | H46: fijo | I46: =VLOOKUP(gastoseventuales[[#This Row],[FECHA]],ventasdiarias[],3,FALSE) -> 24.06 | J46: 240.6 | K46: 40 | L46: =(gastoseventuales[[#This Row],[BS]]/gastoseventuales[[#This Row],[TASA]])+gastoseventuales[[#This Row],[DOLARES]] -> 50
F47: agua | G47: 45000 | H47: EVENTUAL | I47: =VLOOKUP(gastoseventuales[[#This Row],[FECHA]],ventasdiarias[],3,FALSE) -> 24.06 | J47: 6 | L47: =(gastoseventuales[[#This Row],[BS]]/gastoseventuales[[#This Row],[TASA]])+gastoseventuales[[#This Row],[DOLARES]] -> 0.24937656
F48: Retirado para yhamil | G48: 44996 | H48: RETIRADO | I48: =VLOOKUP(gastoseventuales[[#This Row],[FECHA]],ventasdiarias[],3,FALSE) -> 24.13 | K48: 20 | L48: =(gastoseventuales[[#This Row],[BS]]/gastoseventuales[[#This Row],[TASA]])+gastoseventuales[[#This Row],[DOLARES]] -> 20
F49: Joel castellano | G49: 44994 | H49: EVENTUAL | I49: =VLOOKUP(gastoseventuales[[#This Row],[FECHA]],ventasdiarias[],3,FALSE) -> 24.16 | K49: 160 | L49: =(gastoseventuales[[#This Row],[BS]]/gastoseventuales[[#This Row],[TASA]])+gastoseventuales[[#This Row],[DOLARES]] -> 160
F61: MEGAFIBRA | G61: 44956 | H61: fijo | I61: =VLOOKUP(gastoseventuales[[#This Row],[FECHA]],ventasdiarias[],3,FALSE) -> 21.96 | K61: 40 | L61: =(gastoseventuales[[#This Row],[BS]]/gastoseventuales[[#This Row],[TASA]])+gastoseventuales[[#This Row],[DOLARES]] -> 40
F62: YHAMIL GOMEZ PADRE INTERESES | G62: 44956 | H62: fijo | I62: =VLOOKUP(gastoseventuales[[#This Row],[FECHA]],ventasdiarias[],3,FALSE) -> 21.96 | K62: 50 | L62: =(gastoseventuales[[#This Row],[BS]]/gastoseventuales[[#This Row],[TASA]])+gastoseventuales[[#This Row],[DOLARES]] -> 50
F63: alquiler local | G63: 44956 | H63: FIJO | I63: =VLOOKUP(gastoseventuales[[#This Row],[FECHA]],ventasdiarias[],3,FALSE) -> 21.96 | K63: 400 | L63: =(gastoseventuales[[#This Row],[BS]]/gastoseventuales[[#This Row],[TASA]])+gastoseventuales[[#This Row],[DOLARES]] -> 400
F64: NOMINA ULTIMO | G64: 44956 | H64: FIJO | I64: =VLOOKUP(gastoseventuales[[#This Row],[FECHA]],ventasdiarias[],3,FALSE) -> 21.96 | K64: 50 | L64: =(gastoseventuales[[#This Row],[BS]]/gastoseventuales[[#This Row],[TASA]])+gastoseventuales[[#This Row],[DOLARES]] -> 50
F65: ELTON ULTIMO | G65: 44956 | H65: FIJO | I65: =VLOOKUP(gastoseventuales[[#This Row],[FECHA]],ventasdiarias[],3,FALSE) -> 21.96 | K65: 20 | L65: =(gastoseventuales[[#This Row],[BS]]/gastoseventuales[[#This Row],[TASA]])+gastoseventuales[[#This Row],[DOLARES]] -> 20
F66: contadores mes y islr | G66: 44956 | H66: fijo | I66: =VLOOKUP(gastoseventuales[[#This Row],[FECHA]],ventasdiarias[],3,FALSE) -> 21.96 | J66: 768.5 | L66: =(gastoseventuales[[#This Row],[BS]]/gastoseventuales[[#This Row],[TASA]])+gastoseventuales[[#This Row],[DOLARES]] -> 34.995446
F67: Honorarios de impuesto sobre la renta | G67: 44953 | H67: FIJO | I67: =VLOOKUP(gastoseventuales[[#This Row],[FECHA]],ventasdiarias[],3,FALSE) -> 21.72 | J67: 1303.2 | L67: =(gastoseventuales[[#This Row],[BS]]/gastoseventuales[[#This Row],[TASA]])+gastoseventuales[[#This Row],[DOLARES]] -> 60
F68: Condominio de Yhamil (Enero) | G68: 44952 | H68: RETIRADO | I68: =VLOOKUP(gastoseventuales[[#This Row],[FECHA]],ventasdiarias[],3,FALSE) -> 21.31 | J68: 249 | L68: =(gastoseventuales[[#This Row],[BS]]/gastoseventuales[[#This Row],[TASA]])+gastoseventuales[[#This Row],[DOLARES]] -> 11.684655
F69: Telefono de yhamil | G69: 44951 | H69: RETIRADO | I69: =VLOOKUP(gastoseventuales[[#This Row],[FECHA]],ventasdiarias[],3,FALSE) -> 21.17 | J69: 243.48 | L69: =(gastoseventuales[[#This Row],[BS]]/gastoseventuales[[#This Row],[TASA]])+gastoseventuales[[#This Row],[DOLARES]] -> 11.501181
F70: pago cantv | G70: 44950 | H70: fijo | I70: =VLOOKUP(gastoseventuales[[#This Row],[FECHA]],ventasdiarias[],3,FALSE) -> 20.73 | J70: 98.69 | L70: =(gastoseventuales[[#This Row],[BS]]/gastoseventuales[[#This Row],[TASA]])+gastoseventuales[[#This Row],[DOLARES]] -> 4.7607332
F71: Caucho y tripa de moto | G71: 44946 | H71: EVENTUAL | I71: =VLOOKUP(gastoseventuales[[#This Row],[FECHA]],ventasdiarias[],3,FALSE) -> 20.29 | K71: 30 | L71: =(gastoseventuales[[#This Row],[BS]]/gastoseventuales[[#This Row],[TASA]])+gastoseventuales[[#This Row],[DOLARES]] -> 30
F72: SERVICIO (Actividad economica) | G72: 44946 | H72: fijo | I72: =VLOOKUP(gastoseventuales[[#This Row],[FECHA]],ventasdiarias[],3,FALSE) -> 20.29 | J72: 40.58 | L72: =(gastoseventuales[[#This Row],[BS]]/gastoseventuales[[#This Row],[TASA]])+gastoseventuales[[#This Row],[DOLARES]] -> 2
F73: DIVA ACTIVIDAD ECONOMICA | G73: 44946 | H73: fijo | I73: =VLOOKUP(gastoseventuales[[#This Row],[FECHA]],ventasdiarias[],3,FALSE) -> 20.29 | J73: 275.91 | L73: =(gastoseventuales[[#This Row],[BS]]/gastoseventuales[[#This Row],[TASA]])+gastoseventuales[[#This Row],[DOLARES]] -> 13.598324
F74: ELTON QUINCENAL | G74: 44944 | H74: FIJO | I74: =VLOOKUP(gastoseventuales[[#This Row],[FECHA]],ventasdiarias[],3,FALSE) -> 19.98 | K74: 20 | L74: =(gastoseventuales[[#This Row],[BS]]/gastoseventuales[[#This Row],[TASA]])+gastoseventuales[[#This Row],[DOLARES]] -> 20
F75: NOMINA QUINCENAL | G75: 44942 | H75: FIJO | I75: =VLOOKUP(gastoseventuales[[#This Row],[FECHA]],ventasdiarias[],3,FALSE) -> 19.66 | J75: 194.5 | K75: 40 | L75: =(gastoseventuales[[#This Row],[BS]]/gastoseventuales[[#This Row],[TASA]])+gastoseventuales[[#This Row],[DOLARES]] -> 49.893184
F76: PAGOS DE IVA ATRASADO | G76: 44942 | H76: EVENTUAL | I76: =VLOOKUP(gastoseventuales[[#This Row],[FECHA]],ventasdiarias[],3,FALSE) -> 19.66 | J76: 332.42 | L76: =(gastoseventuales[[#This Row],[BS]]/gastoseventuales[[#This Row],[TASA]])+gastoseventuales[[#This Row],[DOLARES]] -> 16.908444
F77: PAGOS DE IVA ATRASADO | G77: 44942 | H77: EVENTUAL | I77: =VLOOKUP(gastoseventuales[[#This Row],[FECHA]],ventasdiarias[],3,FALSE) -> 19.66 | J77: 407.2 | L77: =(gastoseventuales[[#This Row],[BS]]/gastoseventuales[[#This Row],[TASA]])+gastoseventuales[[#This Row],[DOLARES]] -> 20.712106
F78: PAGOS DE IVA ATRASADO | G78: 44942 | H78: EVENTUAL | I78: =VLOOKUP(gastoseventuales[[#This Row],[FECHA]],ventasdiarias[],3,FALSE) -> 19.66 | J78: 318.65 | L78: =(gastoseventuales[[#This Row],[BS]]/gastoseventuales[[#This Row],[TASA]])+gastoseventuales[[#This Row],[DOLARES]] -> 16.208037
F79: PAGOS DE IVA ATRASADO | G79: 44942 | H79: EVENTUAL | I79: =VLOOKUP(gastoseventuales[[#This Row],[FECHA]],ventasdiarias[],3,FALSE) -> 19.66 | J79: 5.43 | L79: =(gastoseventuales[[#This Row],[BS]]/gastoseventuales[[#This Row],[TASA]])+gastoseventuales[[#This Row],[DOLARES]] -> 0.27619532
F80: Liquidacion carlos | G80: 44939 | H80: EVENTUAL | I80: =VLOOKUP(gastoseventuales[[#This Row],[FECHA]],ventasdiarias[],3,FALSE) -> 19.28 | J80: 106.82 | K80: 40 | L80: =(gastoseventuales[[#This Row],[BS]]/gastoseventuales[[#This Row],[TASA]])+gastoseventuales[[#This Row],[DOLARES]] -> 45.540456
F81: copias de llaves | G81: 44936 | H81: EVENTUAL | I81: =VLOOKUP(gastoseventuales[[#This Row],[FECHA]],ventasdiarias[],3,FALSE) -> 18.61 | K81: 5 | L81: =(gastoseventuales[[#This Row],[BS]]/gastoseventuales[[#This Row],[TASA]])+gastoseventuales[[#This Row],[DOLARES]] -> 5
F82: Cantv de yhamil | G82: 44931 | H82: RETIRADO | I82: 18 | J82: 212.98 | L82: =(gastoseventuales[[#This Row],[BS]]/gastoseventuales[[#This Row],[TASA]])+gastoseventuales[[#This Row],[DOLARES]] -> 11.832222
F83: Adelanto chuchi (inter) | G83: 44930 | H83: fijo | I83: 18 | J83: 198 | L83: =(gastoseventuales[[#This Row],[BS]]/gastoseventuales[[#This Row],[TASA]])+gastoseventuales[[#This Row],[DOLARES]] -> 11
F84: ELTON ULTIMO | G84: 44926 | H84: FIJO | I84: =VLOOKUP(gastoseventuales[[#This Row],[FECHA]],ventasdiarias[],3,FALSE) -> 17.49 | L84: =(gastoseventuales[[#This Row],[BS]]/gastoseventuales[[#This Row],[TASA]])+gastoseventuales[[#This Row],[DOLARES]] -> 0
F85: ALQUILER LOCAL | G85: 44925 | H85: FIJO | I85: =VLOOKUP(gastoseventuales[[#This Row],[FECHA]],ventasdiarias[],3,FALSE) -> 17.28 | L85: =(gastoseventuales[[#This Row],[BS]]/gastoseventuales[[#This Row],[TASA]])+gastoseventuales[[#This Row],[DOLARES]] -> 0
F86: ALQUILER LOCAL | G86: 44925 | H86: FIJO | I86: =VLOOKUP(gastoseventuales[[#This Row],[FECHA]],ventasdiarias[],3,FALSE) -> 17.28 | L86: =(gastoseventuales[[#This Row],[BS]]/gastoseventuales[[#This Row],[TASA]])+gastoseventuales[[#This Row],[DOLARES]] -> 0
F87: SERVICIO (Actividad economica) | G87: 44925 | H87: FIJO | I87: =VLOOKUP(gastoseventuales[[#This Row],[FECHA]],ventasdiarias[],3,FALSE) -> 17.28 | L87: =(gastoseventuales[[#This Row],[BS]]/gastoseventuales[[#This Row],[TASA]])+gastoseventuales[[#This Row],[DOLARES]] -> 0
F88: CONTADORES | G88: 44925 | H88: FIJO | I88: =VLOOKUP(gastoseventuales[[#This Row],[FECHA]],ventasdiarias[],3,FALSE) -> 17.28 | L88: =(gastoseventuales[[#This Row],[BS]]/gastoseventuales[[#This Row],[TASA]])+gastoseventuales[[#This Row],[DOLARES]] -> 0
F89: MEGAFIBRA | G89: 44925 | H89: FIJO | I89: =VLOOKUP(gastoseventuales[[#This Row],[FECHA]],ventasdiarias[],3,FALSE) -> 17.28 | L89: =(gastoseventuales[[#This Row],[BS]]/gastoseventuales[[#This Row],[TASA]])+gastoseventuales[[#This Row],[DOLARES]] -> 0
F90: YHAMIL GOMEZ PADRE INTERESES | G90: 44925 | H90: FIJO | I90: =VLOOKUP(gastoseventuales[[#This Row],[FECHA]],ventasdiarias[],3,FALSE) -> 17.28 | L90: =(gastoseventuales[[#This Row],[BS]]/gastoseventuales[[#This Row],[TASA]])+gastoseventuales[[#This Row],[DOLARES]] -> 0
F91: NOMINA ULTIMO | G91: 44925 | H91: FIJO | I91: =VLOOKUP(gastoseventuales[[#This Row],[FECHA]],ventasdiarias[],3,FALSE) -> 17.28 | L91: =(gastoseventuales[[#This Row],[BS]]/gastoseventuales[[#This Row],[TASA]])+gastoseventuales[[#This Row],[DOLARES]] -> 0
F92: CARNE (LA VICTORIA) | G92: 44925 | H92: RETIRADO | I92: =VLOOKUP(gastoseventuales[[#This Row],[FECHA]],ventasdiarias[],3,FALSE) -> 17.28 | L92: =(gastoseventuales[[#This Row],[BS]]/gastoseventuales[[#This Row],[TASA]])+gastoseventuales[[#This Row],[DOLARES]] -> 0
F93: CARNE (LA VICTORIA) | G93: 44925 | H93: RETIRADO | I93: =VLOOKUP(gastoseventuales[[#This Row],[FECHA]],ventasdiarias[],3,FALSE) -> 17.28 | L93: =(gastoseventuales[[#This Row],[BS]]/gastoseventuales[[#This Row],[TASA]])+gastoseventuales[[#This Row],[DOLARES]] -> 0
F94: PASTICHO (TROPIC) | G94: 44925 | H94: RETIRADO | I94: =VLOOKUP(gastoseventuales[[#This Row],[FECHA]],ventasdiarias[],3,FALSE) -> 17.28 | L94: =(gastoseventuales[[#This Row],[BS]]/gastoseventuales[[#This Row],[TASA]])+gastoseventuales[[#This Row],[DOLARES]] -> 0
F95: ACE | G95: 44924 | H95: RETIRADO | I95: =VLOOKUP(gastoseventuales[[#This Row],[FECHA]],ventasdiarias[],3,FALSE) -> 17.11 | L95: =(gastoseventuales[[#This Row],[BS]]/gastoseventuales[[#This Row],[TASA]])+gastoseventuales[[#This Row],[DOLARES]] -> 0
... F115: DULCE LECHOSA | G115: 44917 | H115: RETIRADO | I115: =VLOOKUP(gastoseventuales[[#This Row],[FECHA]],ventasdiarias[],3,FALSE) -> 16.18 | L115: =(gastoseventuales[[#This Row],[BS]]/gastoseventuales[[#This Row],[TASA]])+gastoseventuales[[#This Row],[DOLARES]] -> 0
F116: PAGO ATRASADO DE ALQUILER | G116: 44915 | H116: FIJO | I116: =VLOOKUP(gastoseventuales[[#This Row],[FECHA]],ventasdiarias[],3,FALSE) -> 16 | K116: 400 | L116: =(gastoseventuales[[#This Row],[BS]]/gastoseventuales[[#This Row],[TASA]])+gastoseventuales[[#This Row],[DOLARES]] -> 400
F117: PAGO SENIAT (IVA) | G117: 44910 | H117: FIJO | I117: =VLOOKUP(gastoseventuales[[#This Row],[FECHA]],ventasdiarias[],3,FALSE) -> 15.24 | L117: =(gastoseventuales[[#This Row],[BS]]/gastoseventuales[[#This Row],[TASA]])+gastoseventuales[[#This Row],[DOLARES]] -> 0
F118: NOMINA QUINCENAL | G118: 44910 | H118: FIJO | I118: =VLOOKUP(gastoseventuales[[#This Row],[FECHA]],ventasdiarias[],3,FALSE) -> 15.24 | L118: =(gastoseventuales[[#This Row],[BS]]/gastoseventuales[[#This Row],[TASA]])+gastoseventuales[[#This Row],[DOLARES]] -> 0
F119: CONDOMINIO | G119: 44910 | H119: FIJO | I119: =VLOOKUP(gastoseventuales[[#This Row],[FECHA]],ventasdiarias[],3,FALSE) -> 15.24 | L119: =(gastoseventuales[[#This Row],[BS]]/gastoseventuales[[#This Row],[TASA]])+gastoseventuales[[#This Row],[DOLARES]] -> 0
F120: DIVA ACTIVIDAD ECONOMICA | G120: 44905 | H120: FIJO | I120: =VLOOKUP(gastoseventuales[[#This Row],[FECHA]],ventasdiarias[],3,FALSE) -> 13.6 | J120: 219.04 | L120: =(gastoseventuales[[#This Row],[BS]]/gastoseventuales[[#This Row],[TASA]])+gastoseventuales[[#This Row],[DOLARES]] -> 16.105882
F121: CANTV (APARTMENTO YHAMIL) | G121: 44905 | H121: FIJO | I121: =VLOOKUP(gastoseventuales[[#This Row],[FECHA]],ventasdiarias[],3,FALSE) -> 13.6 | L121: =(gastoseventuales[[#This Row],[BS]]/gastoseventuales[[#This Row],[TASA]])+gastoseventuales[[#This Row],[DOLARES]] -> 0

Sheet Pagos
A2: DEUDA TOTAL | B2: =SUMIFS(PAGOS[DEUDA],PAGOS[ESTADO],"EN DEUDA")-SUMIFS(PAGOS[CANCELADO],PAGOS[ESTADO],"EN DEUDA") -> 4484.9301
A3: EXCESO ABONADO | B3: =SUMIFS(PAGOS[CANCELADO],PAGOS[ESTADO],"EXCEDIDO")-SUMIFS(PAGOS[DEUDA],PAGOS[ESTADO],"EXCEDIDO") -> 0
A4: SALDO ACTUAL | B4: =(Resumen!C9+Resumen!C10)-B5 -> -194.90776
A5: TOTAL ABONOS | B5: =SUMIFS(abonos[ABONO],abonos[FECHA],">="&DATE(Resumen!C2,Resumen!B2,1),abonos[FECHA],"<="&EOMONTH(DATE(Resumen!C2,Resumen!B2,1),0)) -> 1554
A7: NRO FACTURA | B7: VENCIMIENTO | C7: PROVEEDOR | D7: ESTADO | E7: DEUDA | F7: CANCELADO | G7: Pendiente | I7: REFERENCIA | J7: RPOVEEDOR | K7: Tasa | L7: Bs | M7: DOLARES | N7: ABONO | O7: FECHA
A8: 159 | B8: 44972 | C8: ToyoMayor | D8: =_xlfn.IFS(AND(PAGOS[[#This Row],[Pendiente]]<1,PAGOS[[#This Row],[Pendiente]]>-1),"PAGADO",PAGOS[[#This Row],[Pendiente]]>=1,"EN DEUDA") -> EN DEUDA | E8: 3045.95 | F8: =SUMIFS(abonos[ABONO],abonos[REFERENCIA],PAGOS[[#This Row],[NRO FACTURA]]) -> 2000 | G8: =PAGOS[[#This Row],[DEUDA]]-PAGOS[[#This Row],[CANCELADO]] -> 1045.95 | I8: 16040 | J8: =VLOOKUP(abonos[[#This Row],[REFERENCIA]],PAGOS[],3,FALSE) -> inversiones gomas y bases | K8: =abonos[[#This Row],[Bs]]/(VLOOKUP(abonos[[#This Row],[REFERENCIA]],PAGOS[],5,FALSE)) -> 0 | M8: 100 | N8: =abonos[[#This Row],[DOLARES]]+(IF(K8>0,abonos[[#This Row],[Bs]]/abonos[[#This Row],[Tasa]],"0")) -> 100 | O8: 45065
A9: 9859 | B9: 44980 | C9: century | D9: =_xlfn.IFS(AND(PAGOS[[#This Row],[Pendiente]]<1,PAGOS[[#This Row],[Pendiente]]>-1),"PAGADO",PAGOS[[#This Row],[Pendiente]]>=1,"EN DEUDA") -> EN DEUDA | E9: 17.28 | F9: =SUMIFS(abonos[ABONO],abonos[REFERENCIA],PAGOS[[#This Row],[NRO FACTURA]]) -> 0 | G9: =PAGOS[[#This Row],[DEUDA]]-PAGOS[[#This Row],[CANCELADO]] -> 17.28 | I9: 3362 | J9: =VLOOKUP(abonos[[#This Row],[REFERENCIA]],PAGOS[],3,FALSE) -> soldven | K9: =abonos[[#This Row],[Bs]]/(VLOOKUP(abonos[[#This Row],[REFERENCIA]],PAGOS[],5,FALSE)) -> 0 | M9: 80 | N9: =abonos[[#This Row],[DOLARES]]+(IF(K9>0,abonos[[#This Row],[Bs]]/abonos[[#This Row],[Tasa]],"0")) -> 80 | O9: 45072
A10: 424 | B10: 45024 | C10: ToyoMayor | D10: =_xlfn.IFS(AND(PAGOS[[#This Row],[Pendiente]]<1,PAGOS[[#This Row],[Pendiente]]>-1),"PAGADO",PAGOS[[#This Row],[Pendiente]]>=1,"EN DEUDA") -> EN DEUDA | E10: 611.04 | F10: =SUMIFS(abonos[ABONO],abonos[REFERENCIA],PAGOS[[#This Row],[NRO FACTURA]]) -> 0 | G10: =PAGOS[[#This Row],[DEUDA]]-PAGOS[[#This Row],[CANCELADO]] -> 611.04 | I10: 3362 | J10: =VLOOKUP(abonos[[#This Row],[REFERENCIA]],PAGOS[],3,FALSE) -> soldven | K10: =abonos[[#This Row],[Bs]]/(VLOOKUP(abonos[[#This Row],[REFERENCIA]],PAGOS[],5,FALSE)) -> 0 | M10: 40 | N10: =abonos[[#This Row],[DOLARES]]+(IF(K10>0,abonos[[#This Row],[Bs]]/abonos[[#This Row],[Tasa]],"0")) -> 40 | O10: 45064
A11: 3362 | B11: 45046 | C11: soldven | D11: =_xlfn.IFS(AND(PAGOS[[#This Row],[Pendiente]]<1,PAGOS[[#This Row],[Pendiente]]>-1),"PAGADO",PAGOS[[#This Row],[Pendiente]]>=1,"EN DEUDA") -> EN DEUDA | E11: 328 | F11: =SUMIFS(abonos[ABONO],abonos[REFERENCIA],PAGOS[[#This Row],[NRO FACTURA]]) -> 320 | G11: =PAGOS[[#This Row],[DEUDA]]-PAGOS[[#This Row],[CANCELADO]] -> 8 | I11: 14126 | J11: =VLOOKUP(abonos[[#This Row],[REFERENCIA]],PAGOS[],3,FALSE) -> motomastro | K11: 25.48 | L11: 178.36 | N11: =abonos[[#This Row],[DOLARES]]+(IF(K11>0,abonos[[#This Row],[Bs]]/abonos[[#This Row],[Tasa]],"0")) -> 7 | O11: 45062
A12: 16040 | B12: 45048 | C12: inversiones gomas y bases | D12: =_xlfn.IFS(AND(PAGOS[[#This Row],[Pendiente]]<1,PAGOS[[#This Row],[Pendiente]]>-1),"PAGADO",PAGOS[[#This Row],[Pendiente]]>=1,"EN DEUDA") -> EN DEUDA | E12: 140.24 | F12: =SUMIFS(abonos[ABONO],abonos[REFERENCIA],PAGOS[[#This Row],[NRO FACTURA]]) -> 100 | G12: =PAGOS[[#This Row],[DEUDA]]-PAGOS[[#This Row],[CANCELADO]] -> 40.24 | I12: 14126 | J12: =VLOOKUP(abonos[[#This Row],[REFERENCIA]],PAGOS[],3,FALSE) -> motomastro | K12: =abonos[[#This Row],[Bs]]/(VLOOKUP(abonos[[#This Row],[REFERENCIA]],PAGOS[],5,FALSE)) -> 0 | M12: 300 | N12: =abonos[[#This Row],[DOLARES]]+(IF(K12>0,abonos[[#This Row],[Bs]]/abonos[[#This Row],[Tasa]],"0")) -> 300 | O12: 45062
A13: 14126 | B13: 45044 | C13: motomastro | D13: =_xlfn.IFS(AND(PAGOS[[#This Row],[Pendiente]]<1,PAGOS[[#This Row],[Pendiente]]>-1),"PAGADO",PAGOS[[#This Row],[Pendiente]]>=1,"EN DEUDA") -> PAGADO | E13: 307.85 | F13: =SUMIFS(abonos[ABONO],abonos[REFERENCIA],PAGOS[[#This Row],[NRO FACTURA]]) -> 307 | G13: =PAGOS[[#This Row],[DEUDA]]-PAGOS[[#This Row],[CANCELADO]] -> 0.85 | I13: 159 | J13: =VLOOKUP(abonos[[#This Row],[REFERENCIA]],PAGOS[],3,FALSE) -> ToyoMayor | K13: =abonos[[#This Row],[Bs]]/(VLOOKUP(abonos[[#This Row],[REFERENCIA]],PAGOS[],5,FALSE)) -> 0 | M13: 200 | N13: =abonos[[#This Row],[DOLARES]]+(IF(K13>0,abonos[[#This Row],[Bs]]/abonos[[#This Row],[Tasa]],"0")) -> 200 | O13: 45058
A14: 12907 | B14: 45034 | C14: Junquicars | D14: =_xlfn.IFS(AND(PAGOS[[#This Row],[Pendiente]]<1,PAGOS[[#This Row],[Pendiente]]>-1),"PAGADO",PAGOS[[#This Row],[Pendiente]]>=1,"EN DEUDA") -> EN DEUDA | E14: 360.01 | F14: =SUMIFS(abonos[ABONO],abonos[REFERENCIA],PAGOS[[#This Row],[NRO FACTURA]]) -> 0 | G14: =PAGOS[[#This Row],[DEUDA]]-PAGOS[[#This Row],[CANCELADO]] -> 360.01 | I14: 3362 | J14: =VLOOKUP(abonos[[#This Row],[REFERENCIA]],PAGOS[],3,FALSE) -> soldven | K14: =abonos[[#This Row],[Bs]]/(VLOOKUP(abonos[[#This Row],[REFERENCIA]],PAGOS[],5,FALSE)) -> 0 | M14: 200 | N14: =abonos[[#This Row],[DOLARES]]+(IF(K14>0,abonos[[#This Row],[Bs]]/abonos[[#This Row],[Tasa]],"0")) -> 200 | O14: 45054
A15: 4120 | B15: 45043 | C15: Medina Motors | D15: =_xlfn.IFS(AND(PAGOS[[#This Row],[Pendiente]]<1,PAGOS[[#This Row],[Pendiente]]>-1),"PAGADO",PAGOS[[#This Row],[Pendiente]]>=1,"EN DEUDA") -> EN DEUDA | E15: 501.3 | F15: =SUMIFS(abonos[ABONO],abonos[REFERENCIA],PAGOS[[#This Row],[NRO FACTURA]]) -> 0 | G15: =PAGOS[[#This Row],[DEUDA]]-PAGOS[[#This Row],[CANCELADO]] -> 501.3 | I15: 159 | J15: =VLOOKUP(abonos[[#This Row],[REFERENCIA]],PAGOS[],3,FALSE) -> ToyoMayor | K15: =abonos[[#This Row],[Bs]]/(VLOOKUP(abonos[[#This Row],[REFERENCIA]],PAGOS[],5,FALSE)) -> 0 | M15: 200 | N15: =abonos[[#This Row],[DOLARES]]+(IF(K15>0,abonos[[#This Row],[Bs]]/abonos[[#This Row],[Tasa]],"0")) -> 200 | O15: 45044
A16: 12908 | B16: 45034 | C16: Junquicars | D16: =_xlfn.IFS(AND(PAGOS[[#This Row],[Pendiente]]<1,PAGOS[[#This Row],[Pendiente]]>-1),"PAGADO",PAGOS[[#This Row],[Pendiente]]>=1,"EN DEUDA") -> EN DEUDA | E16: 155.12 | F16: =SUMIFS(abonos[ABONO],abonos[REFERENCIA],PAGOS[[#This Row],[NRO FACTURA]]) -> 0 | G16: =PAGOS[[#This Row],[DEUDA]]-PAGOS[[#This Row],[CANCELADO]] -> 155.12 | I16: 7001 | J16: =VLOOKUP(abonos[[#This Row],[REFERENCIA]],PAGOS[],3,FALSE) -> M&T inveriones | K16: 24.57 | L16: 316.46 | M16: 20 | N16: =abonos[[#This Row],[DOLARES]]+(IF(K16>0,abonos[[#This Row],[Bs]]/abonos[[#This Row],[Tasa]],"0")) -> 32.879935 | O16: 45037
A17: 7001 | B17: 44973 | C17: M&T inveriones | D17: =_xlfn.IFS(AND(PAGOS[[#This Row],[Pendiente]]<1,PAGOS[[#This Row],[Pendiente]]>-1),"PAGADO",PAGOS[[#This Row],[Pendiente]]>=1,"EN DEUDA") -> EN DEUDA | E17: 1732.88 | F17: =SUMIFS(abonos[ABONO],abonos[REFERENCIA],PAGOS[[#This Row],[NRO FACTURA]]) -> 832.87993 | G17: =PAGOS[[#This Row],[DEUDA]]-PAGOS[[#This Row],[CANCELADO]] -> 900.00007 | I17: 159 | J17: =VLOOKUP(abonos[[#This Row],[REFERENCIA]],PAGOS[],3,FALSE) -> ToyoMayor | K17: =abonos[[#This Row],[Bs]]/(VLOOKUP(abonos[[#This Row],[REFERENCIA]],PAGOS[],5,FALSE)) -> 0 | M17: 400 | N17: =abonos[[#This Row],[DOLARES]]+(IF(K17>0,abonos[[#This Row],[Bs]]/abonos[[#This Row],[Tasa]],"0")) -> 400 | O17: 45037
A18: 1277 | B18: 44966 | C18: cegaC | D18: =_xlfn.IFS(AND(PAGOS[[#This Row],[Pendiente]]<1,PAGOS[[#This Row],[Pendiente]]>-1),"PAGADO",PAGOS[[#This Row],[Pendiente]]>=1,"EN DEUDA") -> EN DEUDA | E18: 588.66 | F18: =SUMIFS(abonos[ABONO],abonos[REFERENCIA],PAGOS[[#This Row],[NRO FACTURA]]) -> 0 | G18: =PAGOS[[#This Row],[DEUDA]]-PAGOS[[#This Row],[CANCELADO]] -> 588.66 | I18: 7001 | J18: =VLOOKUP(abonos[[#This Row],[REFERENCIA]],PAGOS[],3,FALSE) -> M&T inveriones | K18: =abonos[[#This Row],[Bs]]/(VLOOKUP(abonos[[#This Row],[REFERENCIA]],PAGOS[],5,FALSE)) -> 0 | M18: 100 | N18: =abonos[[#This Row],[DOLARES]]+(IF(K18>0,abonos[[#This Row],[Bs]]/abonos[[#This Row],[Tasa]],"0")) -> 100 | O18: 45029
A19: 3229 | B19: 44976 | C19: soldven | D19: =_xlfn.IFS(AND(PAGOS[[#This Row],[Pendiente]]<1,PAGOS[[#This Row],[Pendiente]]>-1),"PAGADO",PAGOS[[#This Row],[Pendiente]]>=1,"EN DEUDA") -> PAGADO | E19: 404 | F19: =SUMIFS(abonos[ABONO],abonos[REFERENCIA],PAGOS[[#This Row],[NRO FACTURA]]) -> 404 | G19: =PAGOS[[#This Row],[DEUDA]]-PAGOS[[#This Row],[CANCELADO]] -> 0 | I19: 159 | J19: =VLOOKUP(abonos[[#This Row],[REFERENCIA]],PAGOS[],3,FALSE) -> ToyoMayor | K19: =abonos[[#This Row],[Bs]]/(VLOOKUP(abonos[[#This Row],[REFERENCIA]],PAGOS[],5,FALSE)) -> 0 | M19: 400 | N19: =abonos[[#This Row],[DOLARES]]+(IF(K19>0,abonos[[#This Row],[Bs]]/abonos[[#This Row],[Tasa]],"0")) -> 400 | O19: 45027
A20: PLATO | B20: 44994 | C20: Junior guevara | D20: =_xlfn.IFS(AND(PAGOS[[#This Row],[Pendiente]]<1,PAGOS[[#This Row],[Pendiente]]>-1),"PAGADO",PAGOS[[#This Row],[Pendiente]]>=1,"EN DEUDA") -> PAGADO | E20: 50 | F20: =SUMIFS(abonos[ABONO],abonos[REFERENCIA],PAGOS[[#This Row],[NRO FACTURA]]) -> 50 | G20: =PAGOS[[#This Row],[DEUDA]]-PAGOS[[#This Row],[CANCELADO]] -> 0 | I20: 600 | J20: =VLOOKUP(abonos[[#This Row],[REFERENCIA]],PAGOS[],3,FALSE) -> Vifa Electronics | K20: =abonos[[#This Row],[Bs]]/(VLOOKUP(abonos[[#This Row],[REFERENCIA]],PAGOS[],5,FALSE)) -> 0 | M20: 138.15 | N20: =abonos[[#This Row],[DOLARES]]+(IF(K20>0,abonos[[#This Row],[Bs]]/abonos[[#This Row],[Tasa]],"0")) -> 138.15 | O20: 45021
A21: 600 | B21: 45031 | C21: Vifa Electronics | D21: =_xlfn.IFS(AND(PAGOS[[#This Row],[Pendiente]]<1,PAGOS[[#This Row],[Pendiente]]>-1),"PAGADO",PAGOS[[#This Row],[Pendiente]]>=1,"EN DEUDA") -> PAGADO | E21: 138.15 | F21: =SUMIFS(abonos[ABONO],abonos[REFERENCIA],PAGOS[[#This Row],[NRO FACTURA]]) -> 138.15 | G21: =PAGOS[[#This Row],[DEUDA]]-PAGOS[[#This Row],[CANCELADO]] -> 0 | I21: 7001 | J21: =VLOOKUP(abonos[[#This Row],[REFERENCIA]],PAGOS[],3,FALSE) -> M&T inveriones | K21: =abonos[[#This Row],[Bs]]/(VLOOKUP(abonos[[#This Row],[REFERENCIA]],PAGOS[],5,FALSE)) -> 0 | M21: 200 | N21: =abonos[[#This Row],[DOLARES]]+(IF(K21>0,abonos[[#This Row],[Bs]]/abonos[[#This Row],[Tasa]],"0")) -> 200 | O21: 45015
A22: 164 | B22: 45048 | C22: Rengifo | D22: =_xlfn.IFS(AND(PAGOS[[#This Row],[Pendiente]]<1,PAGOS[[#This Row],[Pendiente]]>-1),"PAGADO",PAGOS[[#This Row],[Pendiente]]>=1,"EN DEUDA") -> EN DEUDA | E22: 257.33 | F22: =SUMIFS(abonos[ABONO],abonos[REFERENCIA],PAGOS[[#This Row],[NRO FACTURA]]) -> 0 | G22: =PAGOS[[#This Row],[DEUDA]]-PAGOS[[#This Row],[CANCELADO]] -> 257.33 | I22: 3229 | J22: =VLOOKUP(abonos[[#This Row],[REFERENCIA]],PAGOS[],3,FALSE) -> soldven | K22: =abonos[[#This Row],[Bs]]/(VLOOKUP(abonos[[#This Row],[REFERENCIA]],PAGOS[],5,FALSE)) -> 0 | M22: 64 | N22: =abonos[[#This Row],[DOLARES]]+(IF(K22>0,abonos[[#This Row],[Bs]]/abonos[[#This Row],[Tasa]],"0")) -> 64 | O22: 45012
D23: =_xlfn.IFS(AND(PAGOS[[#This Row],[Pendiente]]<1,PAGOS[[#This Row],[Pendiente]]>-1),"PAGADO",PAGOS[[#This Row],[Pendiente]]>=1,"EN DEUDA") -> PAGADO | F23: =SUMIFS(abonos[ABONO],abonos[REFERENCIA],PAGOS[[#This Row],[NRO FACTURA]]) -> 0 | G23: =PAGOS[[#This Row],[DEUDA]]-PAGOS[[#This Row],[CANCELADO]] -> 0 | I23: 159 | J23: =VLOOKUP(abonos[[#This Row],[REFERENCIA]],PAGOS[],3,FALSE) -> ToyoMayor | K23: =abonos[[#This Row],[Bs]]/(VLOOKUP(abonos[[#This Row],[REFERENCIA]],PAGOS[],5,FALSE)) -> 0 | M23: 300 | N23: =abonos[[#This Row],[DOLARES]]+(IF(K23>0,abonos[[#This Row],[Bs]]/abonos[[#This Row],[Tasa]],"0")) -> 300 | O23: 45008
I24: 7001 | J24: =VLOOKUP(abonos[[#This Row],[REFERENCIA]],PAGOS[],3,FALSE) -> M&T inveriones | K24: =abonos[[#This Row],[Bs]]/(VLOOKUP(abonos[[#This Row],[REFERENCIA]],PAGOS[],5,FALSE)) -> 0 | M24: 100 | N24: =abonos[[#This Row],[DOLARES]]+(IF(K24>0,abonos[[#This Row],[Bs]]/abonos[[#This Row],[Tasa]],"0")) -> 100 | O24: 45008
I25: 3229 | J25: =VLOOKUP(abonos[[#This Row],[REFERENCIA]],PAGOS[],3,FALSE) -> soldven | K25: =abonos[[#This Row],[Bs]]/(VLOOKUP(abonos[[#This Row],[REFERENCIA]],PAGOS[],5,FALSE)) -> 0 | M25: 40 | N25: =abonos[[#This Row],[DOLARES]]+(IF(K25>0,abonos[[#This Row],[Bs]]/abonos[[#This Row],[Tasa]],"0")) -> 40 | O25: 45006
I26: 3229 | J26: =VLOOKUP(abonos[[#This Row],[REFERENCIA]],PAGOS[],3,FALSE) -> soldven | K26: =abonos[[#This Row],[Bs]]/(VLOOKUP(abonos[[#This Row],[REFERENCIA]],PAGOS[],5,FALSE)) -> 0 | M26: 300 | N26: =abonos[[#This Row],[DOLARES]]+(IF(K26>0,abonos[[#This Row],[Bs]]/abonos[[#This Row],[Tasa]],"0")) -> 300 | O26: 44998
I27: PLATO | J27: =VLOOKUP(abonos[[#This Row],[REFERENCIA]],PAGOS[],3,FALSE) -> Junior guevara | K27: =abonos[[#This Row],[Bs]]/(VLOOKUP(abonos[[#This Row],[REFERENCIA]],PAGOS[],5,FALSE)) -> 0 | M27: 50 | N27: =abonos[[#This Row],[DOLARES]]+(IF(K27>0,abonos[[#This Row],[Bs]]/abonos[[#This Row],[Tasa]],"0")) -> 50 | O27: 44994
I28: 159 | J28: =VLOOKUP(abonos[[#This Row],[REFERENCIA]],PAGOS[],3,FALSE) -> ToyoMayor | K28: =abonos[[#This Row],[Bs]]/(VLOOKUP(abonos[[#This Row],[REFERENCIA]],PAGOS[],5,FALSE)) -> 0 | M28: 500 | N28: =abonos[[#This Row],[DOLARES]]+(IF(K28>0,abonos[[#This Row],[Bs]]/abonos[[#This Row],[Tasa]],"0")) -> 500 | O28: 44991
I33: 7001 | J33: =VLOOKUP(abonos[[#This Row],[REFERENCIA]],PAGOS[],3,FALSE) -> M&T inveriones | K33: =abonos[[#This Row],[Bs]]/(VLOOKUP(abonos[[#This Row],[REFERENCIA]],PAGOS[],5,FALSE)) -> 0 | M33: 400 | N33: =abonos[[#This Row],[DOLARES]]+(IF(K33>0,abonos[[#This Row],[Bs]]/abonos[[#This Row],[Tasa]],"0")) -> 400 | O33: 44957

Sheet Foraneos
H2: TOTAL COSTO | J2: TOTAL VENTA
H3: =SUMIFS(FORANEO[COSTO],FORANEO[[FECHA ]],">="&DATE(Resumen!C2,Resumen!B2,1),FORANEO[[FECHA ]],"<="&EOMONTH(DATE(Resumen!C2,Resumen!B2,1),0)) -> 0 | J3: =SUMIFS(FORANEO[VENTA],FORANEO[[FECHA ]],">="&DATE(Resumen!C2,Resumen!B2,1),FORANEO[[FECHA ]],"<="&EOMONTH(DATE(Resumen!C2,Resumen!B2,1),0)) -> 0
B7: FECHA | C7: COSTO | D7: VENTA | E7: GANANCIA | F7: REPUESTO | G7: FORMA DE PAGO
B8: 44935 | C8: 150 | D8: 170 | E8: =FORANEO[[#This Row],[VENTA]]-FORANEO[[#This Row],[COSTO]] -> 20 | F8: BOMBA DE ACEITE | G8: DOLARES
B9: 45031 | C9: 70 | D9: 90 | E9: =FORANEO[[#This Row],[VENTA]]-FORANEO[[#This Row],[COSTO]] -> 20 | F9: JUEGO DE PISTONES 040 COROLLA 1,8 | G9: DOLARES
B10: 45043 | C10: 35 | D10: 40 | E10: =FORANEO[[#This Row],[VENTA]]-FORANEO[[#This Row],[COSTO]] -> 5 | F10: SENSOR TPS HILUX | G10: DOLARES
E11: =FORANEO[[#This Row],[VENTA]]-FORANEO[[#This Row],[COSTO]] -> 0
